Workbook

Sheet Pivots
A3: Row Labels | B3: Sum of Total Efforts | C3: % Allocation
A4: A5 | B4: 7266 | C4: 0.22903073
A5: B1 | B5: 7549.5 | C5: 0.2379669
A6: B2 | B6: 8095.5 | C6: 0.2551773
A7: C1 | B7: 2635.5 | C7: 0.083073286
A8: C2 | B8: 4226.25 | C8: 0.13321513
A9: D1 | B9: 420 | C9: 0.013238771
A10: D2 | B10: 850.5 | C10: 0.026808511
A11: E1 | B11: 682.5 | C11: 0.021513002
A12: Grand Total | B12: 31725.75 | C12: =SUM(C4:C11) -> 1.0000236
A14: Row Labels | B14: Sum of Total
A15: India | B15: 0.89789839
A16: US | B16: 0.10210161
A17: Grand Total | B17: 1

Sheet Estimator 4 RL
G1: =SUM(G4:G123) -> 5.75 | H1: =SUM(H4:H123) -> 24 | I1: =SUM(I4:I123) -> 43.5 | J1: =SUM(J4:J123) -> 68.5 | K1: =SUM(K4:K123) -> 84 | L1: =SUM(L4:L123) -> 87 | M1: =SUM(M4:M123) -> 87 | N1: =SUM(N4:N123) -> 87 | ... AC1: =SUM(AC4:AC123) -> 31725.75
G2: May | H2: Jun | I2: Jul | J2: Aug | K2: Sep | L2: Oct | M2: Nov | N2: Dec | O2: Jan | P2: Feb | Q2: Mar | R2: Apr | S2: May | T2: Jun | U2: Jul | V2: Aug | W2: Sep | X2: Oct | Y2: Nov | Z2: Dec | AA2: Jan
A3: BU | B3: Team | C3: Role | D3: Local Grade | E3: Global Grade | F3: Shore | G3: M1 | H3: M2 | I3: M3 | J3: M4 | K3: M5 | L3: M6 | M3: M7 | N3: M8 | O3: M9 | P3: M10 | Q3: M11 | R3: M12 | S3: M13 | T3: M14 | U3: M15 | V3: M16 | W3: M17 | X3: M18 | Y3: M19 | Z3: M20 | AA3: M21 | AB3: Total Months | AC3: Total Efforts
A4: NA I&D | B4: Governance | C4: Engagement Lead | D4: D | E4: D2 | F4: US | G4: 1 | H4: 1 | I4: 1 | J4: 1 | K4: 1 | L4: 1 | M4: 1 | N4: 1 | O4: 1 | P4: 1 | Q4: 1 | R4: 1 | S4: 1 | T4: 1 | U4: 1 | V4: 1 | W4: 1 | X4: 1 | Y4: 1 | Z4: 1 | AA4: 0.5 | AB4: =SUM(G4:AA4) -> 20.5 | AC4: =AB4*21 -> 430.5
A5: GCP | B5: Governance | C5: Offshore Delivery Lead | D5: E | E5: E1 | F5: India | G5: 1 | H5: 1 | I5: 1 | J5: 1 | K5: 1 | L5: 1 | M5: 1 | N5: 1 | O5: 1 | P5: 1 | Q5: 1 | R5: 1 | S5: 1 | T5: 1 | U5: 1 | V5: 1 | W5: 1 | X5: 1 | Y5: 1 | Z5: 1 | AA5: 0.5 | AB5: =SUM(G5:AA5) -> 20.5 | AC5: =AB5*21 -> 430.5
A6: NA I&D | B6: Architecture | C6: Data Architect | D6: C | E6: C2 | F6: US | G6: 1 | H6: 1 | I6: 1 | J6: 1 | K6: 1 | L6: 1 | M6: 1 | N6: 1 | O6: 1 | P6: 1 | Q6: 1 | R6: 1 | S6: 1 | T6: 1 | U6: 1 | V6: 1 | W6: 1 | X6: 1 | Y6: 1 | Z6: 1 | AB6: =SUM(G6:AA6) -> 20 | AC6: =AB6*21 -> 420
A7: GCP | B7: Architecture | C7: Solution Architect | D7: D | E7: D2 | F7: India | G7: 1 | H7: 1 | I7: 1 | J7: 1 | K7: 1 | L7: 1 | M7: 1 | N7: 1 | O7: 1 | P7: 1 | Q7: 1 | R7: 1 | S7: 1 | T7: 1 | U7: 1 | V7: 1 | W7: 1 | X7: 1 | Y7: 1 | Z7: 1 | AB7: =SUM(G7:AA7) -> 20 | AC7: =AB7*21 -> 420
A8: NA I&D | B8: Architecture | C8: Platform/Cloud Architect | D8: C | E8: C2 | F8: US | G8: 0.75 | H8: 1 | I8: 1 | J8: 1 | AB8: =SUM(G8:AA8) -> 3.75 | AC8: =AB8*21 -> 78.75
A9: GCP | B9: Architecture | C9: Platform/Cloud Architect | D9: D | E9: D1 | F9: India | G9: 1 | H9: 1 | I9: 1 | J9: 1 | K9: 1 | L9: 1 | M9: 1 | N9: 1 | O9: 1 | P9: 1 | Q9: 1 | R9: 1 | S9: 1 | T9: 1 | U9: 1 | V9: 1 | W9: 1 | X9: 1 | Y9: 1 | Z9: 1 | AB9: =SUM(G9:AA9) -> 20 | AC9: =AB9*21 -> 420
A10: Testing | B10: Quality Assurance | C10: QA Lead | D10: C | E10: C2 | F10: US | H10: 1 | I10: 1 | J10: 1 | K10: 1 | L10: 1 | M10: 1 | N10: 1 | O10: 1 | P10: 1 | Q10: 1 | R10: 1 | S10: 1 | T10: 1 | U10: 1 | V10: 1 | W10: 1 | X10: 1 | Y10: 1 | Z10: 1 | AB10: =SUM(G10:AA10) -> 19 | AC10: =AB10*21 -> 399
A11: NA I&D | B11: Requrements | C11: Lead Analyst | D11: C | E11: C1 | F11: US | H11: 1 | I11: 1 | J11: 1 | K11: 1 | L11: 1 | M11: 1 | N11: 1 | O11: 1 | P11: 1 | Q11: 1 | R11: 1 | S11: 1 | T11: 1 | U11: 1 | V11: 1 | W11: 1 | X11: 1 | Y11: 1 | Z11: 1 | AB11: =SUM(G11:AA11) -> 19 | AC11: =AB11*21 -> 399
A12: NA I&D | B12: Requrements | C12: Data Analyst 1 | D12: B | E12: B2 | F12: US | H12: 1 | I12: 1 | J12: 1 | K12: 1 | L12: 1 | M12: 1 | N12: 1 | O12: 1 | P12: 1 | Q12: 1 | R12: 1 | S12: 1 | T12: 1 | U12: 1 | V12: 1 | W12: 1 | X12: 1 | Y12: 1 | Z12: 1 | AA12: 1 | AB12: =SUM(G12:AA12) -> 20 | AC12: =AB12*21 -> 420
A13: GCP | B13: Requrements | C13: Data Analyst 2 | D13: B | E13: B2 | F13: India | H13: 1 | I13: 1 | J13: 1 | K13: 1 | L13: 1 | M13: 1 | N13: 1 | O13: 1 | P13: 1 | Q13: 1 | R13: 1 | S13: 1 | T13: 1 | U13: 1 | V13: 1 | W13: 1 | X13: 1 | Y13: 1 | Z13: 1 | AB13: =SUM(G13:AA13) -> 19 | AC13: =AB13*21 -> 399
A14: GCP | B14: Requrements | C14: Data Analyst 3 | D14: B | E14: B1 | F14: India | H14: 1 | I14: 1 | J14: 1 | K14: 1 | L14: 1 | M14: 1 | N14: 1 | O14: 1 | P14: 1 | Q14: 1 | R14: 1 | S14: 1 | T14: 1 | U14: 1 | V14: 1 | W14: 1 | X14: 1 | Y14: 1 | Z14: 1 | AA14: 1 | AB14: =SUM(G14:AA14) -> 20 | AC14: =AB14*21 -> 420
A15: GCP | B15: Platform & DevOps | C15: DevOps SME | D15: C | E15: C1 | F15: India | H15: 0.5 | I15: 1 | J15: 1 | K15: 1 | L15: 1 | M15: 1 | N15: 1 | O15: 1 | P15: 1 | Q15: 1 | R15: 1 | S15: 1 | T15: 1 | U15: 1 | V15: 1 | W15: 1 | X15: 1 | Y15: 1 | Z15: 1 | AB15: =SUM(G15:AA15) -> 18.5 | AC15: =AB15*21 -> 388.5
A16: IDEA | B16: Platform & DevOps | C16: IDEA SME | D16: E | E16: E1 | F16: India | H16: 1 | I16: 1 | J16: 1 | K16: 1 | L16: 1 | M16: 1 | N16: 1 | O16: 1 | P16: 1 | Q16: 1 | R16: 1 | S16: 1 | AB16: =SUM(G16:AA16) -> 12 | AC16: =AB16*21 -> 252
A17: IDEA | B17: Platform & DevOps | C17: IDEA SME | D17: B | E17: B2 | F17: India | H17: 1 | I17: 1 | J17: 1 | K17: 1 | L17: 1 | M17: 1 | N17: 1 | O17: 1 | P17: 1 | Q17: 1 | R17: 1 | S17: 1 | T17: 1 | U17: 1 | V17: 1 | W17: 1 | X17: 1 | Y17: 1 | Z17: 1 | AB17: =SUM(G17:AA17) -> 19 | AC17: =AB17*21 -> 399
A18: NA I&D | B18: Reverse Engineering | C18: ETL SME (Inf + TD) | D18: B | E18: B2 | F18: US | H18: 1 | I18: 1 | J18: 1 | K18: 1 | L18: 1 | M18: 1 | N18: 1 | O18: 1 | P18: 1 | Q18: 1 | R18: 1 | S18: 1 | T18: 1 | U18: 1 | V18: 1 | W18: 1 | AB18: =SUM(G18:AA18) -> 16 | AC18: =AB18*21 -> 336
A19: EDE | B19: Reverse Engineering | C19: Teradata SME | D19: C | E19: C2 | F19: India | H19: 1 | I19: 1 | J19: 1 | K19: 1 | L19: 1 | M19: 1 | N19: 1 | O19: 1 | P19: 1 | Q19: 1 | R19: 1 | S19: 1 | T19: 1 | U19: 1 | V19: 1 | W19: 1 | X19: 1 | Y19: 1 | Z19: 1 | AB19: =SUM(G19:AA19) -> 19 | AC19: =AB19*21 -> 399
A20: EDE | B20: Reverse Engineering | C20: Informatica SME | D20: C | E20: C1 | F20: India | H20: 1 | I20: 1 | J20: 1 | K20: 1 | L20: 1 | M20: 1 | N20: 1 | O20: 1 | P20: 1 | Q20: 1 | R20: 1 | S20: 1 | T20: 1 | U20: 1 | V20: 1 | W20: 1 | AB20: =SUM(G20:AA20) -> 16 | AC20: =AB20*21 -> 336
A21: EDE | B21: Reverse Engineering | C21: Informatica SME | D21: B | E21: B1 | F21: India | H21: 1 | I21: 1 | J21: 1 | K21: 1 | L21: 1 | M21: 1 | N21: 1 | O21: 1 | P21: 1 | Q21: 1 | R21: 1 | S21: 1 | T21: 1 | U21: 1 | V21: 1 | W21: 1 | X21: 1 | Y21: 1 | Z21: 1 | AB21: =SUM(G21:AA21) -> 19 | AC21: =AB21*21 -> 399
A22: GCP | B22: Schema Migration | C22: Schema Migration Lead | D22: C | E22: C2 | F22: India | H22: 0.5 | I22: 1 | J22: 1 | K22: 1 | L22: 1 | M22: 1 | N22: 1 | O22: 1 | P22: 1 | Q22: 1 | R22: 1 | S22: 1 | T22: 1 | U22: 1 | V22: 1 | W22: 1 | X22: 1 | Y22: 1 | AB22: =SUM(G22:AA22) -> 17.5 | AC22: =AB22*21 -> 367.5
A23: GCP | B23: Schema Migration | C23: Developer (GCP) | D23: B | E23: B2 | F23: India | I23: 1 | J23: 1 | K23: 1 | L23: 1 | M23: 1 | N23: 1 | O23: 1 | P23: 1 | Q23: 1 | R23: 1 | S23: 1 | T23: 1 | U23: 1 | V23: 1 | W23: 1 | X23: 1 | Y23: 1 | Z23: 1 | AB23: =SUM(G23:AA23) -> 18 | AC23: =AB23*21 -> 378
A24: GCP | B24: Schema Migration | C24: Developer (GCP) | D24: A | E24: A5 | F24: India | I24: 0.5 | J24: 1 | K24: 1 | L24: 1 | M24: 1 | N24: 1 | O24: 1 | P24: 1 | Q24: 1 | R24: 1 | S24: 1 | T24: 1 | U24: 1 | V24: 1 | W24: 1 | X24: 1 | Y24: 1 | Z24: 1 | AB24: =SUM(G24:AA24) -> 17.5 | AC24: =AB24*21 -> 367.5
A25: GCP | B25: Data Migration 1 | C25: Data Migration Lead | D25: C | E25: C2 | F25: India | H25: 0.5 | I25: 1 | J25: 1 | K25: 1 | L25: 1 | M25: 1 | N25: 1 | O25: 1 | P25: 1 | Q25: 1 | R25: 1 | S25: 1 | T25: 1 | U25: 1 | V25: 1 | W25: 1 | X25: 1 | Y25: 1 | Z25: 1 | AB25: =SUM(G25:AA25) -> 18.5 | AC25: =AB25*21 -> 388.5
A26: NA I&D | B26: Data Migration 1 | C26: Developer (GCP) | D26: B | E26: B2 | F26: US | H26: 0.5 | I26: 1 | J26: 1 | K26: 1 | L26: 1 | M26: 1 | N26: 1 | O26: 1 | P26: 1 | Q26: 1 | R26: 1 | S26: 1 | T26: 1 | U26: 1 | V26: 1 | W26: 1 | X26: 1 | Y26: 1 | Z26: 1 | AB26: =SUM(G26:AA26) -> 18.5 | AC26: =AB26*21 -> 388.5
A27: GCP | B27: Data Migration 1 | C27: Developer (GCP)/ Tester | D27: B | E27: B1 | F27: India | H27: 0.5 | I27: 1.5 | J27: 2 | K27: 2 | L27: 2 | M27: 2 | N27: 2 | O27: 2 | P27: 2 | Q27: 2 | R27: 2 | S27: 2 | T27: 2 | U27: 2 | V27: 2 | W27: 2 | X27: 2 | Y27: 2 | Z27: 1 | AA27: 1 | AB27: =SUM(G27:AA27) -> 36 | AC27: =AB27*21 -> 756
A28: GCP | B28: Data Migration 1 | C28: Developer (GCP) | D28: A | E28: A5 | F28: India | H28: 0.5 | I28: 1.5 | J28: 2 | K28: 2 | L28: 2 | M28: 2 | N28: 2 | O28: 2 | P28: 2 | Q28: 2 | R28: 2 | S28: 2 | T28: 2 | U28: 2 | V28: 2 | W28: 2 | X28: 2 | Y28: 2 | Z28: 1 | AA28: 1 | AB28: =SUM(G28:AA28) -> 36 | AC28: =AB28*21 -> 756
A29: GCP | B29: Data Migration 2 | C29: Data Migration Lead | D29: C | E29: C1 | F29: India | I29: 0.5 | J29: 1 | K29: 1 | L29: 1 | M29: 1 | N29: 1 | O29: 1 | P29: 1 | Q29: 1 | R29: 1 | S29: 1 | T29: 1 | U29: 1 | V29: 1 | W29: 1 | X29: 1 | Y29: 1 | Z29: 1 | AB29: =SUM(G29:AA29) -> 17.5 | AC29: =AB29*21 -> 367.5
A30: NA I&D | B30: Data Migration 2 | C30: Developer (GCP) | D30: B | E30: B2 | F30: US | I30: 0.5 | J30: 1 | K30: 1 | L30: 1 | M30: 1 | N30: 1 | O30: 1 | P30: 1 | Q30: 1 | R30: 1 | S30: 1 | T30: 1 | U30: 1 | V30: 1 | W30: 1 | X30: 1 | Y30: 1 | Z30: 1 | AB30: =SUM(G30:AA30) -> 17.5 | AC30: =AB30*21 -> 367.5
A31: GCP | B31: Data Migration 2 | C31: Developer (GCP)/ Tester | D31: B | E31: B1 | F31: India | I31: 0.5 | J31: 1.5 | K31: 3 | L31: 3 | M31: 3 | N31: 3 | O31: 3 | P31: 3 | Q31: 3 | R31: 3 | S31: 3 | T31: 3 | U31: 3 | V31: 3 | W31: 3 | X31: 3 | Y31: 3 | Z31: 2 | AA31: 1 | AB31: =SUM(G31:AA31) -> 50 | AC31: =AB31*21 -> 1050
A32: GCP | B32: Data Migration 2 | C32: Developer (GCP) | D32: A | E32: A5 | F32: India | I32: 0.5 | J32: 1.5 | K32: 2 | L32: 2 | M32: 2 | N32: 2 | O32: 2 | P32: 2 | Q32: 2 | R32: 2 | S32: 2 | T32: 2 | U32: 2 | V32: 2 | W32: 2 | X32: 2 | Y32: 2 | Z32: 2 | AA32: 1 | AB32: =SUM(G32:AA32) -> 35 | AC32: =AB32*21 -> 735
A33: GCP | B33: Data Ingestion 1 | C33: Data Ingestion Lead | D33: C | E33: C2 | F33: India | H33: 0.5 | I33: 1 | J33: 1 | K33: 1 | L33: 1 | M33: 1 | N33: 1 | O33: 1 | P33: 1 | Q33: 1 | R33: 1 | S33: 1 | T33: 1 | U33: 1 | V33: 1 | W33: 1 | X33: 1 | Y33: 1 | AB33: =SUM(G33:AA33) -> 17.5 | AC33: =AB33*21 -> 367.5
A34: GCP | B34: Data Ingestion 1 | C34: Developer (GCP) | D34: B | E34: B2 | F34: India | H34: 0.5 | I34: 2 | J34: 2 | K34: 2 | L34: 2 | M34: 2 | N34: 2 | O34: 2 | P34: 2 | Q34: 2 | R34: 2 | S34: 2 | T34: 2 | U34: 2 | V34: 2 | W34: 2 | X34: 2 | Y34: 2 | Z34: 2 | AA34: 1 | AB34: =SUM(G34:AA34) -> 37.5 | AC34: =AB34*21 -> 787.5
A35: GCP | B35: Data Ingestion 1 | C35: Developer (GCP)/ Tester | D35: B | E35: B1 | F35: India | H35: 0.5 | I35: 1.5 | J35: 2 | K35: 2 | L35: 2 | M35: 2 | N35: 2 | O35: 2 | P35: 2 | Q35: 2 | R35: 2 | S35: 2 | T35: 2 | U35: 2 | V35: 2 | W35: 2 | X35: 2 | Y35: 2 | Z35: 1 | AA35: 1 | AB35: =SUM(G35:AA35) -> 36 | AC35: =AB35*21 -> 756
A36: GCP | B36: Data Ingestion 1 | C36: Developer (GCP)/ Tester | D36: A | E36: A5 | F36: India | H36: 0.5 | I36: 1.5 | J36: 2 | K36: 2 | L36: 2 | M36: 2 | N36: 2 | O36: 2 | P36: 2 | Q36: 2 | R36: 2 | S36: 2 | T36: 2 | U36: 2 | V36: 2 | W36: 2 | X36: 2 | AB36: =SUM(G36:AA36) -> 32 | AC36: =AB36*21 -> 672
A37: GCP | B37: Data Ingestion 2 | C37: Data Ingestion Lead | D37: C | E37: C2 | F37: India | J37: 1 | K37: 1 | L37: 1 | M37: 1 | N37: 1 | O37: 1 | P37: 1 | Q37: 1 | R37: 1 | S37: 1 | T37: 1 | U37: 1 | V37: 1 | W37: 1 | X37: 1 | Y37: 1 | AB37: =SUM(G37:AA37) -> 16 | AC37: =AB37*21 -> 336
A38: GCP | B38: Data Ingestion 2 | C38: Developer (GCP) | D38: B | E38: B2 | F38: India | J38: 1 | K38: 2 | L38: 2 | M38: 2 | N38: 2 | O38: 2 | P38: 2 | Q38: 2 | R38: 2 | S38: 2 | T38: 2 | U38: 2 | V38: 1 | W38: 1 | X38: 1 | Y38: 1 | Z38: 1 | AA38: 1 | AB38: =SUM(G38:AA38) -> 29 | AC38: =AB38*21 -> 609
A39: GCP | B39: Data Ingestion 2 | C39: Developer (GCP)/ Tester | D39: B | E39: B1 | F39: India | J39: 1 | K39: 2 | L39: 2 | M39: 2 | N39: 2 | O39: 2 | P39: 2 | Q39: 2 | R39: 2 | S39: 2 | T39: 2 | U39: 2 | V39: 2 | W39: 2 | X39: 1 | Y39: 1 | Z39: 1 | AA39: 1 | AB39: =SUM(G39:AA39) -> 31 | AC39: =AB39*21 -> 651
A40: GCP | B40: Data Ingestion 2 | C40: Developer (GCP)/ Tester | D40: A | E40: A5 | F40: India | J40: 1 | K40: 2 | L40: 2 | M40: 2 | N40: 2 | O40: 2 | P40: 2 | Q40: 2 | R40: 2 | S40: 2 | T40: 2 | U40: 2 | V40: 2 | W40: 2 | X40: 2 | AB40: =SUM(G40:AA40) -> 29 | AC40: =AB40*21 -> 609
A41: GCP | B41: Data Distillation 1 | C41: Data Distillation Lead | D41: C | E41: C2 | F41: India | I41: 1 | J41: 1 | K41: 1 | L41: 1 | M41: 1 | N41: 1 | O41: 1 | P41: 1 | Q41: 1 | R41: 1 | S41: 1 | T41: 1 | U41: 1 | V41: 1 | W41: 1 | X41: 1 | Y41: 1 | Z41: 1 | AB41: =SUM(G41:AA41) -> 18 | AC41: =AB41*21 -> 378
A42: GCP | B42: Data Distillation 1 | C42: Developer (GCP) | D42: C | E42: C1 | F42: India | AB42: =SUM(G42:AA42) -> 0 | AC42: =AB42*21 -> 0
A43: GCP | B43: Data Distillation 1 | C43: Developer (GCP) | D43: B | E43: B2 | F43: India | I43: 1 | J43: 2 | K43: 2 | L43: 2 | M43: 2 | N43: 2 | O43: 2 | P43: 2 | Q43: 2 | R43: 2 | S43: 2 | T43: 2 | U43: 2 | V43: 2 | W43: 2 | X43: 2 | Y43: 2 | Z43: 2 | AA43: 1 | AB43: =SUM(G43:AA43) -> 36 | AC43: =AB43*21 -> 756
A44: GCP | B44: Data Distillation 1 | C44: Developer (GCP)/ Tester | D44: B | E44: B1 | F44: India | I44: 1 | J44: 2 | K44: 2 | L44: 2 | M44: 2 | N44: 2 | O44: 2 | P44: 2 | Q44: 2 | R44: 2 | S44: 2 | T44: 2 | U44: 2 | V44: 2 | W44: 2 | X44: 2 | Y44: 2 | Z44: 2 | AA44: 1 | AB44: =SUM(G44:AA44) -> 36 | AC44: =AB44*21 -> 756
A45: GCP | B45: Data Distillation 1 | C45: Developer (GCP)/ Tester | D45: A | E45: A5 | F45: India | I45: 1 | J45: 2 | K45: 2 | L45: 2 | M45: 2 | N45: 2 | O45: 2 | P45: 2 | Q45: 2 | R45: 2 | S45: 2 | T45: 2 | U45: 2 | V45: 2 | W45: 2 | X45: 2 | Y45: 2 | Z45: 2 | AA45: 1 | AB45: =SUM(G45:AA45) -> 36 | AC45: =AB45*21 -> 756
A46: GCP | B46: Data Distillation 2 | C46: Data Distillation Lead | D46: C | E46: C2 | F46: India | J46: 1 | K46: 1 | L46: 1 | M46: 1 | N46: 1 | O46: 1 | P46: 1 | Q46: 1 | R46: 1 | S46: 1 | T46: 1 | U46: 1 | V46: 1 | W46: 1 | X46: 1 | Y46: 1 | Z46: 1 | AB46: =SUM(G46:AA46) -> 17 | AC46: =AB46*21 -> 357
A47: GCP | B47: Data Distillation 2 | C47: Developer (GCP) | D47: C | E47: C1 | F47: India | AB47: =SUM(G47:AA47) -> 0 | AC47: =AB47*21 -> 0
A48: GCP | B48: Data Distillation 2 | C48: Developer (GCP) | D48: B | E48: B2 | F48: India | J48: 1 | K48: 2 | L48: 2 | M48: 2 | N48: 2 | O48: 2 | P48: 2 | Q48: 2 | R48: 2 | S48: 2 | T48: 2 | U48: 2 | V48: 2 | W48: 2 | X48: 2 | Y48: 2 | Z48: 2 | AA48: 1 | AB48: =SUM(G48:AA48) -> 34 | AC48: =AB48*21 -> 714
A49: GCP | B49: Data Distillation 2 | C49: Developer (GCP)/ Tester | D49: B | E49: B1 | F49: India | J49: 1 | K49: 2 | L49: 2 | M49: 2 | N49: 2 | O49: 2 | P49: 2 | Q49: 2 | R49: 2 | S49: 2 | T49: 2 | U49: 2 | V49: 2 | W49: 2 | X49: 2 | Y49: 2 | Z49: 2 | AA49: 1 | AB49: =SUM(G49:AA49) -> 34 | AC49: =AB49*21 -> 714
A50: GCP | B50: Data Distillation 2 | C50: Developer (GCP)/ Tester | D50: A | E50: A5 | F50: India | J50: 1 | K50: 2 | L50: 2 | M50: 2 | N50: 2 | O50: 2 | P50: 2 | Q50: 2 | R50: 2 | S50: 2 | T50: 2 | U50: 2 | V50: 2 | W50: 2 | X50: 2 | Y50: 2 | Z50: 2 | AA50: 1 | AB50: =SUM(G50:AA50) -> 34 | AC50: =AB50*21 -> 714
A51: GCP | B51: Data Distillation 3 | C51: Data Distillation Lead | D51: C | E51: C2 | F51: India | K51: 1 | L51: 1 | M51: 1 | N51: 1 | O51: 1 | P51: 1 | Q51: 1 | R51: 1 | S51: 1 | T51: 1 | U51: 1 | V51: 1 | W51: 1 | X51: 1 | Y51: 1 | Z51: 1 | AB51: =SUM(G51:AA51) -> 16 | AC51: =AB51*21 -> 336
A52: GCP | B52: Data Distillation 3 | C52: Developer (GCP) | D52: C | E52: C1 | F52: India | AB52: =SUM(G52:AA52) -> 0 | AC52: =AB52*21 -> 0
A53: GCP | B53: Data Distillation 3 | C53: Developer (GCP) | D53: B | E53: B2 | F53: India | K53: 1 | L53: 2 | M53: 2 | N53: 2 | O53: 2 | P53: 2 | Q53: 2 | R53: 2 | S53: 2 | T53: 2 | U53: 2 | V53: 2 | W53: 2 | X53: 2 | Y53: 2 | Z53: 2 | AA53: 1 | AB53: =SUM(G53:AA53) -> 32 | AC53: =AB53*21 -> 672
A54: GCP | B54: Data Distillation 3 | C54: Developer (GCP)/ Tester | D54: B | E54: B1 | F54: India | K54: 1 | L54: 2 | M54: 2 | N54: 2 | O54: 2 | P54: 2 | Q54: 2 | R54: 2 | S54: 2 | T54: 2 | U54: 2 | V54: 2 | W54: 2 | X54: 2 | Y54: 2 | Z54: 2 | AA54: 1 | AB54: =SUM(G54:AA54) -> 32 | AC54: =AB54*21 -> 672
A55: GCP | B55: Data Distillation 3 | C55: Developer (GCP)/ Tester | D55: A | E55: A5 | F55: India | K55: 1 | L55: 2 | M55: 2 | N55: 2 | O55: 2 | P55: 2 | Q55: 2 | R55: 2 | S55: 2 | T55: 2 | U55: 2 | V55: 2 | W55: 2 | X55: 2 | Y55: 2 | Z55: 2 | AA55: 1 | AB55: =SUM(G55:AA55) -> 32 | AC55: =AB55*21 -> 672
A56: DCX | B56: UI Development | C56: UI Developer/ Angular | D56: B | E56: B2 | F56: India | J56: 0.5 | K56: 1 | L56: 0.5 | AB56: =SUM(G56:AA56) -> 2 | AC56: =AB56*21 -> 42
A57: DCX | B57: UI Development | C57: UI Developer/ Angular | D57: B | E57: B2 | F57: India | J57: 0.5 | K57: 1 | L57: 0.5 | AB57: =SUM(G57:AA57) -> 2 | AC57: =AB57*21 -> 42
A58: AI&A | B58: Governance | C58: Offshore Reporting Lead | D58: C | E58: C2 | F58: India | H58: 1 | I58: 1 | J58: 1 | K58: 1 | L58: 1 | M58: 1 | N58: 1 | O58: 1 | P58: 1 | Q58: 1 | R58: 1 | S58: 1 | T58: 1 | U58: 1 | V58: 1 | W58: 1 | X58: 1 | Y58: 1 | Z58: 1 | AB58: =SUM(G58:AA58) -> 19 | AC58: =AB58*21 -> 399
A59: AI&A | B59: Report Repoint (Q/T) | C59: Report Developer | D59: B | E59: B2 | F59: India | J59: 0.5 | K59: 1 | L59: 1 | M59: 1 | N59: 1 | O59: 1 | P59: 1 | Q59: 1 | R59: 1 | S59: 1 | T59: 1 | U59: 1 | V59: 1 | W59: 1 | X59: 1 | Y59: 1 | Z59: 1 | AA59: 1 | AB59: =SUM(G59:AA59) -> 17.5 | AC59: =AB59*21 -> 367.5
A60: AI&A | B60: Report Repoint (SAP) | C60: Report Developer | D60: C | E60: C1 | F60: India | I60: 1 | J60: 1 | K60: 1 | L60: 1 | M60: 1 | N60: 1 | O60: 1 | P60: 1 | Q60: 1 | R60: 1 | S60: 1 | T60: 1 | U60: 1 | V60: 1 | W60: 1 | X60: 1 | Y60: 1 | Z60: 1 | AB60: =SUM(G60:AA60) -> 18 | AC60: =AB60*21 -> 378
A61: AI&A | B61: Report Repoint (SAP) | C61: Report Developer | D61: B | E61: B2 | F61: India | I61: 1 | J61: 1 | K61: 1 | L61: 1 | M61: 1 | N61: 1 | O61: 1 | P61: 1 | Q61: 1 | R61: 1 | S61: 1 | T61: 1 | U61: 1 | V61: 1 | W61: 1 | X61: 1 | Y61: 1 | Z61: 1 | AA61: 1 | AB61: =SUM(G61:AA61) -> 19 | AC61: =AB61*21 -> 399
A62: AI&A | B62: Report Repoint (SAP) | C62: Report Developer / Tester | D62: B | E62: B1 | F62: India | J62: 0.5 | K62: 1 | L62: 1 | M62: 1 | N62: 1 | O62: 1 | P62: 1 | Q62: 1 | R62: 1 | S62: 1 | T62: 1 | U62: 1 | V62: 1 | W62: 1 | X62: 1 | Y62: 1 | Z62: 1 | AA62: 1 | AB62: =SUM(G62:AA62) -> 17.5 | AC62: =AB62*21 -> 367.5
A63: AI&A | B63: Report Repoint (SAP) | C63: Report Developer / Tester | D63: A | E63: A5 | F63: India | J63: 0.5 | K63: 1 | L63: 1.5 | M63: 2 | N63: 2 | O63: 2 | P63: 2 | Q63: 2 | R63: 2 | S63: 2 | T63: 2 | U63: 2 | V63: 2 | W63: 2 | X63: 2 | Y63: 2 | Z63: 1 | AA63: 1 | AB63: =SUM(G63:AA63) -> 31 | AC63: =AB63*21 -> 651
A64: AI&A | B64: Report Repoint (Tibco) | C64: Report Developer | D64: C | E64: C1 | F64: India | I64: 0.5 | J64: 1 | K64: 1 | L64: 1 | M64: 1 | N64: 1 | O64: 1 | P64: 1 | Q64: 1 | R64: 1 | S64: 1 | T64: 1 | U64: 1 | V64: 1 | W64: 1 | X64: 1 | Y64: 1 | Z64: 1 | AB64: =SUM(G64:AA64) -> 17.5 | AC64: =AB64*21 -> 367.5
A65: AI&A | B65: Report Repoint (Tibco) | C65: Report Developer | D65: B | E65: B2 | F65: India | I65: 0.5 | J65: 1 | K65: 1 | L65: 1 | M65: 1 | N65: 1 | O65: 1 | P65: 1 | Q65: 1 | R65: 1 | S65: 1 | T65: 1 | U65: 1 | V65: 1 | W65: 1 | X65: 1 | Y65: 1 | Z65: 1 | AA65: 1 | AB65: =SUM(G65:AA65) -> 18.5 | AC65: =AB65*21 -> 388.5
A66: AI&A | B66: Report Repoint (Tibco) | C66: Report Developer / Tester | D66: B | E66: B1 | F66: India | J66: 1 | K66: 1 | L66: 1 | M66: 1 | N66: 1 | O66: 1 | P66: 1 | Q66: 1 | R66: 1 | S66: 1 | T66: 1 | U66: 1 | V66: 1 | W66: 1 | X66: 1 | Y66: 1 | Z66: 1 | AA66: 1 | AB66: =SUM(G66:AA66) -> 18 | AC66: =AB66*21 -> 378
A67: AI&A | B67: Report Repoint (Tibco) | C67: Report Developer / Tester | D67: A | E67: A5 | F67: India | J67: 1 | K67: 1 | L67: 1.5 | M67: 2 | N67: 2 | O67: 2 | P67: 2 | Q67: 2 | R67: 2 | S67: 2 | T67: 2 | U67: 2 | V67: 2 | W67: 2 | X67: 2 | Y67: 2 | Z67: 1 | AA67: 1 | AB67: =SUM(G67:AA67) -> 31.5 | AC67: =AB67*21 -> 661.5
A68: Testing | B68: Quality Assurance | C68: Test Lead | D68: C | E68: C1 | F68: India | H68: 1 | I68: 1 | J68: 1 | K68: 1 | L68: 1 | M68: 1 | N68: 1 | O68: 1 | P68: 1 | Q68: 1 | R68: 1 | S68: 1 | T68: 1 | U68: 1 | V68: 1 | W68: 1 | X68: 1 | Y68: 1 | Z68: 1 | AB68: =SUM(G68:AA68) -> 19 | AC68: =AB68*21 -> 399 | AE68: =SUM(AC68:AC71,AC10) -> 2730
A69: Testing | B69: Quality Assurance | C69: Sr Testers | D69: B | E69: B2 | F69: India | I69: 1 | J69: 1 | K69: 2 | L69: 2 | M69: 2 | N69: 2 | O69: 2 | P69: 2 | Q69: 2 | R69: 2 | S69: 2 | T69: 2 | U69: 2 | V69: 1 | W69: 1 | X69: 2 | Y69: 1 | Z69: 1 | AB69: =SUM(G69:AA69) -> 30 | AC69: =AB69*21 -> 630
A70: Testing | B70: Quality Assurance | C70: Tester | D70: B | E70: B1 | F70: India | J70: 2 | K70: 2 | L70: 2 | M70: 2 | N70: 2 | O70: 2 | P70: 2 | Q70: 2 | R70: 2 | S70: 2 | T70: 2 | U70: 2 | V70: 2 | W70: 1 | X70: 1 | Y70: 1 | Z70: 1 | AB70: =SUM(G70:AA70) -> 30 | AC70: =AB70*21 -> 630
A71: Testing | B71: Quality Assurance | C71: Jr Tesers | D71: A | E71: A5 | F71: India | J71: 1 | K71: 2 | L71: 2 | M71: 2 | N71: 2 | O71: 2 | P71: 2 | Q71: 2 | R71: 2 | S71: 2 | T71: 2 | U71: 2 | V71: 2 | W71: 2 | X71: 2 | Y71: 2 | Z71: 1 | AB71: =SUM(G71:AA71) -> 32 | AC71: =AB71*21 -> 672
AB72: =SUM(G72:AA72) -> 0 | AC72: =AB72*21 -> 0
AB73: =SUM(G73:AA73) -> 0 | AC73: =AB73*21 -> 0
AB74: =SUM(G74:AA74) -> 0 | AC74: =AB74*21 -> 0
AB75: =SUM(G75:AA75) -> 0 | AC75: =AB75*21 -> 0
AB76: =SUM(G76:AA76) -> 0 | AC76: =AB76*21 -> 0
AB77: =SUM(G77:AA77) -> 0 | AC77: =AB77*21 -> 0
AB78: =SUM(G78:AA78) -> 0 | AC78: =AB78*21 -> 0
AB79: =SUM(G79:AA79) -> 0 | AC79: =AB79*21 -> 0
AB80: =SUM(G80:AA80) -> 0 | AC80: =AB80*21 -> 0
AB81: =SUM(G81:AA81) -> 0 | AC81: =AB81*21 -> 0
AB82: =SUM(G82:AA82) -> 0 | AC82: =AB82*21 -> 0
AB83: =SUM(G83:AA83) -> 0 | AC83: =AB83*21 -> 0
... AB104: =SUM(G104:AA104) -> 0 | AC104: =AB104*21 -> 0

Sheet Summary
B2: DE | C2: 2697
B3: DS-Predictive | C3: 450
B4: Reporting | C4: 500
C5: =SUM(C2:C4) -> 3647 | E5: =C5/(20*8.5) -> 21.452941

Sheet Data Engineering Efforts
A1: Phase | B1: Efforts | C1: % Add On | D1: Comments
A2: Project Management | B2: =C2*$B$5/$C$5 -> 215.744 | C2: 0.08 | E2: #FTEs 12 Mnths | F2: =B10/(12*20) -> 11.236667
A3: Analysis and Requirement Gathering | B3: =C3*$B$5/$C$5 -> 269.68 | C3: 0.1 | D3: DCX team will do data mapping & transfomration specifications
A4: Design Efforts | B4: =C4*$B$5/$C$5 -> 323.616 | C4: 0.12
A5: Development and Unit Testing | B5: =SUM(N15:N37) -> 1348.4 | C5: 0.5
A6: System(& Integration) Testing | B6: =C6*$B$5/$C$5 -> 323.616 | C6: 0.12
A7: UAT | B7: =C7*$B$5/$C$5 -> 134.84 | C7: 0.05
A8: Deployment & Hypercare | B8: =C8*$B$5/$C$5 -> 80.904 | C8: 0.03
A10: Total Efforts in PDs | B10: =SUM(B2:B9) -> 2696.8 | E10: =2697/(20*12) -> 11.2375
F13: Complexity Distribution | I13: Cut Estimates to Build & Test in PDs | L13: Total Efforts in PDs | M13: % Savings (Reusability/ Tools/ Automations) | N13: PD post Savings | O13: Comments
A14: BU | B14: SL | C14: Object Type | D14: # Objects/ Jobs | E14: Method of Implementation | F14: Simple | G14: Mid | H14: Complex | I14: Simple | J14: Mid | K14: Complex | P14: Avg
A15: I&D | B15: Azure | C15: Data Ingestion Jobs - Batch | D15: 56 | E15: ADB/ADF Jobs for Daata Ingestion incremental Batch | F15: 0.3 | G15: 0.4 | H15: 0.3 | I15: 1 | J15: 2 | K15: 3 | L15: =(D15*F15*I15+D15*G15*J15+D15*H15*K15) -> 112 | M15: 0.4 | N15: =L15*(1-M15) -> 67.2 | O15: Using IDEA Data Ingestion /Azure MX metadata driven approach + Same used for 1st history load | P15: =N15/D15 -> 1.2
A16: DCX | B16: DCX | C16: Data Ingestion Jobs - APIs | D16: 168 | E16: Mulesoft data ingestion jobs using APIs from Souce to RAW (ADLS ) Incremental | F16: 0.3 | G16: 0.4 | H16: 0.3 | I16: 1.5 | J16: 2 | K16: 3.5 | L16: =(D16*F16*I16+D16*G16*J16+D16*H16*K16) -> 386.4 | M16: 0.2 | N16: =L16*(1-M16) -> 309.12 | O16: Parameterizing re-usable jobs & repeating sources + Same used for 1st history load | P16: =N16/D16 -> 1.84
A17: I&D | B17: Azure | C17: Data Ingestion Jobs - Streaming | D17: 56 | E17: Kafka/Confluence Streaming Jobs | F17: 0.3 | G17: 0.4 | H17: 0.3 | I17: 2 | J17: 3 | K17: 4 | L17: =(D17*F17*I17+D17*G17*J17+D17*H17*K17) -> 168 | M17: 0.4 | N17: =L17*(1-M17) -> 100.8 | O17: Using IDEA Data Ingestion /Azure MX metadata driven approach + Same used for 1st history load | P17: =N17/D17 -> 1.8
A18: I&D | B18: Azure | C18: Data Curation/Transformation Jobs - ADF/ADB | D18: 196 | E18: Get quality /enriched data from Profisee & Transorm/curate into Azure Delta Lake using ADF/ADB | F18: 0.3 | G18: 0.4 | H18: 0.3 | I18: 2 | J18: 2.5 | K18: 3 | L18: =(D18*F18*I18+D18*G18*J18+D18*H18*K18) -> 490 | M18: 0.4 | N18: =L18*(1-M18) -> 294 | O18: Using IDEA Data Ingestion /Azure MX metadata driven approach | P18: =N18/D18 -> 1.5
A19: I&D | B19: Azure | C19: Curated/Transformed Jobs to Consuption Layer | D19: 78 | E19: Get curated/transformed data into Consuption/Sementic layer using ADF/ADF in Synapse | F19: 0.3 | G19: 0.4 | H19: 0.3 | I19: 2 | J19: 4 | K19: 6 | L19: =(D19*F19*I19+D19*G19*J19+D19*H19*K19) -> 312 | M19: 0.4 | N19: =L19*(1-M19) -> 187.2 | O19: Using IDEA Data Ingestion /Azure MX metadata driven approach | P19: =N19/D19 -> 2.4
A20: I&D | B20: Azure | C20: ADB/ADF jobs for Downsteam systems | D20: 8 | E20: Get consuption data & send it to downsteam systems using ADF/ADB Batch | F20: 0.3 | G20: 0.4 | H20: 0.3 | I20: 1.5 | J20: 2 | K20: 3 | L20: =(D20*F20*I20+D20*G20*J20+D20*H20*K20) -> 17.2 | M20: 0.4 | N20: =L20*(1-M20) -> 10.32 | O20: Using IDEA Data Ingestion /Azure MX metadata driven approach | P20: =N20/D20 -> 1.29
A21: I&D | B21: Azure | C21: Data Masking Jobs | D21: 56 | E21: Using ADF/ADB for persistant / Azure Dynamic data masking for PII/PCI data | F21: 0.3 | G21: 0.4 | H21: 0.3 | I21: 1 | J21: 2.5 | K21: 4 | L21: =(D21*F21*I21+D21*G21*J21+D21*H21*K21) -> 140 | M21: 0 | N21: =L21*(1-M21) -> 140 | P21: =N21/D21 -> 2.5
A22: I&D | B22: Azure | C22: Job Sheduling efforts 20% of total Jobs | D22: =SUM(D15:D21)*0.2 -> 123.6 | E22: Job sheduling in Airflow/ADF - 20% of total jobs | F22: 0.3 | G22: 0.4 | H22: 0.3 | I22: 0.5 | J22: 1 | K22: 1.5 | L22: =(D22*F22*I22+D22*G22*J22+D22*H22*K22) -> 123.6 | M22: 0 | N22: =L22*(1-M22) -> 123.6 | P22: =N22/D22 -> 1
A23: I&D | B23: Azure | C23: Ci/CD pipelines for Dev-Ops/Infra | D23: 1 | E23: CI-CD dev-ops pipelines (Git/Maven/Jenkins/Arti factory(Nexus)) | F23: 0 | G23: 1 | H23: 0 | I23: 0 | J23: 30 | K23: 0 | L23: =(D23*F23*I23+D23*G23*J23+D23*H23*K23) -> 30 | M23: 0.3 | N23: =L23*(1-M23) -> 21 | O23: IDEA Dev-Ops CI-CD FM | P23: =N23/D23 -> 21
A24: I&D | B24: Azure | C24: ABCR FM Customization | D24: 1 | E24: ABCR FM Customization | F24: 0 | G24: 1 | H24: 0 | I24: 0 | J24: 16 | K24: 0 | L24: =(D24*F24*I24+D24*G24*J24+D24*H24*K24) -> 16 | M24: 0.5 | N24: =L24*(1-M24) -> 8 | O24: IDEA ABCR FM | P24: =N24/D24 -> 8
A25: I&D | B25: Azure | C25: Azure AD Sync up for athentication & Athorization | D25: 1 | E25: Azure AD Sync up for athentication & Athorization | F25: 0 | G25: 1 | H25: 0 | I25: 0 | J25: 10 | K25: 0 | L25: =(D25*F25*I25+D25*G25*J25+D25*H25*K25) -> 10 | M25: 0 | N25: =L25*(1-M25) -> 10
A26: DCX | B26: DCX | C26: CI/CD for Mulesoft/Infra | D26: 1 | E26: Mulesoft CI/CD Setup (Git/Maven/Jenkins/Arti factory(Nexus)) - Customization efforts | F26: 0 | G26: 1 | H26: 0 | I26: 0 | J26: 150 | K26: 0 | L26: 15 | M26: 0 | N26: =L26*(1-M26) -> 15
A27: I&D | B27: Azure | C27: Moving from Landing to Raw Zone | D27: 224 | E27: Format conversion jobs | F27: 0.3 | G27: 0.4 | H27: 0.3 | I27: 0.25 | J27: 1 | K27: 1.5 | L27: =(D27*F27*I27+D27*G27*J27+D27*H27*K27) -> 207.2 | M27: 0.7 | N27: =L27*(1-M27) -> 62.16 | O27: Parameterized for similar file types to standerdize file types
F28: 0.3 | G28: 0.4 | H28: 0.3 | I28: 1.5 | J28: 2 | K28: 3 | L28: =(D28*F28*I28+D28*G28*J28+D28*H28*K28) -> 0 | M28: 0 | N28: =L28*(1-M28) -> 0
F29: 0.3 | G29: 0.4 | H29: 0.3 | I29: 1.5 | J29: 2 | K29: 3 | L29: =(D29*F29*I29+D29*G29*J29+D29*H29*K29) -> 0 | M29: 0 | N29: =L29*(1-M29) -> 0
F30: 0.3 | G30: 0.4 | H30: 0.3 | I30: 1.5 | J30: 2 | K30: 3 | L30: =(D30*F30*I30+D30*G30*J30+D30*H30*K30) -> 0 | M30: 0 | N30: =L30*(1-M30) -> 0
F31: 0.3 | G31: 0.4 | H31: 0.3 | I31: 1.5 | J31: 2 | K31: 3 | L31: =(D31*F31*I31+D31*G31*J31+D31*H31*K31) -> 0 | M31: 0 | N31: =L31*(1-M31) -> 0
F32: 0.3 | G32: 0.4 | H32: 0.3 | I32: 1.5 | J32: 2 | K32: 3 | L32: =(D32*F32*I32+D32*G32*J32+D32*H32*K32) -> 0 | M32: 0 | N32: =L32*(1-M32) -> 0
L39: Without Savings | M39: With Savings
K40: Man-days | L40: =SUM(L15:L37) -> 2027.4 | M40: =SUM(N15:N37) -> 1348.4
L41: % Savings | M41: =(L40-M40)/L40 -> 0.33491171

Sheet Power BI Reports
C2: SCM | D2: 15
C3: Warranty Ana | D3: 5
C4: Planning & FCST | D4: 5

Sheet Predictive-DS
B2: Demand forecasting; Order‑to‑Ship / Order‑to‑Cash forecasting

Sheet Sheet5

Sheet PP-RL Plan
D1: Due Deligence & Blue Print Phase | L1: Execution Phase
D2: Wk1 | E2: Wk2 | F2: Wk3 | G2: Wk4 | H2: Wk5 | I2: Wk6 | J2: Wk7 | K2: Wk8 | L2: M3 | M2: M4 | N2: M5 | O2: M6 | P2: M7 | Q2: M8 | R2: M9
B3: DD & Blueprint Phase | C3: Project Kick-Off
C4: Workshops
C5: Use case priorotization
C6: Platform Options
C7: Platform Foundation | F7: Dev | K7: QA | M7: Prod
C8: Security & access
L9: MVP 1 | N9: MVP 2 | P9: MVP 3
A12: Shore | B12: Grade | C12: Roles | D12: Wk1 | E12: Wk2 | F12: Wk3 | G12: Wk4 | H12: Wk5 | I12: Wk6 | J12: Wk7 | K12: Wk8 | L12: M3 | M12: M4 | N12: M5 | O12: M6 | P12: M7 | Q12: M8 | R12: M9
B13: On | C13: BI Arch | D13: 1 | E13: 1 | F13: 1 | G13: 1 | H13: 1 | I13: 1 | J13: 1 | K13: 1 | L13: 1 | M13: 1 | N13: 1 | O13: 1 | P13: 1 | Q13: 1 | R13: 1
B14: On | C14: Data Modeller | D14: 1 | E14: 1 | F14: 1 | G14: 1 | H14: 1 | I14: 1 | J14: 1 | K14: 1 | L14: 1 | M14: 1 | N14: 1 | O14: 1 | P14: 1 | Q14: 1 | R14: 1
B15: On | C15: BA | D15: 1 | E15: 1 | F15: 1 | G15: 1 | H15: 1 | I15: 1 | J15: 1 | K15: 1 | L15: 1 | M15: 1 | N15: 1 | O15: 1 | P15: 1 | Q15: 1 | R15: 1
B16: Off | C16: Power BI | D16: 1 | E16: 1 | F16: 1 | G16: 1 | H16: 1 | I16: 1 | J16: 1 | K16: 1 | L16: 1 | M16: 1 | N16: 1 | O16: 1 | P16: 1 | Q16: 1 | R16: 1
B17: Off | C17: xx
C18: xx
C19: xx
C20: xx
C21: xx

Sheet Estimator
A1: Phase | B1: Efforts | C1: Comments
A2: Project Management | B2: =$B$5*C2 -> 318.30746 | C2: 0.075
A3: Analysis and Requirement Gathering | B3: =$B$5*C3 -> 275.86646 | C3: 0.065 | E3: ~FTEs | F3: =B10/(16*20) -> 18.833191
A4: Design and Data Modeling | B4: =$B$5*C4 -> 509.29193 | C4: 0.12
A5: Development and Unit Tesing | B5: =SUM(N15:N31) -> 4244.0994 | C5: =SUM(N15:N31) -> 4244.0994
A6: System(& Integration) Testing | B6: =$B$5*C6 -> 403.18945 | C6: 0.095
A7: UAT | B7: =$B$5*C7 -> 190.98447 | C7: 0.045
A8: Deployment | B8: =$B$5*C8 -> 63.661492 | C8: 0.015
A9: KT & Handoff | B9: =$B$5*C9 -> 21.220497 | C9: 0.005
A10: Total Efforts | B10: =SUM(B2:B9) -> 6026.6212
F13: Complexity Matrix | I13: Cut Estimates to Build & Test in Hrs | L13: Total Efforts in PDs | M13: % Savings | N13: PD post Savings | O13: Comments
A14: BU | B14: SL | C14: Object Type | D14: # Objects/ Jobs | E14: Method of Migration | F14: Simple | G14: Mid | H14: Complex | I14: Simple | J14: Mid | K14: Complex
A15: I&D | B15: GCP | C15: No. Of Tables / Files | D15: 15724 | E15: BigQuery Data Transfer APIs (Lift & Shift) | F15: 0.3 | G15: 0.4 | H15: 0.3 | I15: 0.5 | J15: 0.75 | K15: 1 | L15: =(D15*F15*I15+D15*G15*J15+D15*H15*K15)/9 -> 1310.3333 | M15: 0.5 | N15: =L15*(1-M15) -> 655.16667 | O15: Teradata to Big Query schema migration tool to achieve quick conversions BigQuery Data Transfer Service as migration agent for Teradata Compute migration tool for BTEQ to BQ conversion
A16: I&D | B16: GCP | C16: # of Views, Semantic Layer | D16: 25992 | E16: BigQuery Data Transfer APIs (Lift & Shift) | F16: 0.7 | G16: 0.2 | H16: 0.1 | I16: 0.25 | J16: 0.5 | K16: 0.75 | L16: =(D16*F16*I16+D16*G16*J16+D16*H16*K16)/9 -> 1010.8 | M16: 0.5 | N16: =L16*(1-M16) -> 505.4
A17: I&D | B17: Infa | C17: # of ETL views with business Logic | D17: 4052 | E17: Informatica Same logic with minimal retro efforts (Lift & Shift, Reporint) | F17: 1 | G17: 0 | H17: 0 | I17: 3 | J17: 4 | K17: 5 | L17: =(D17*F17*I17+D17*G17*J17+D17*H17*K17)/9 -> 1350.6667 | M17: 0.5 | N17: =L17*(1-M17) -> 675.33333 | O17: No code change, only change connection , retrofication & smoke test
A18: I&D | B18: GCP | C18: Informatica Transformation in GBQ SP | D18: 2148 | E18: BigQuery Data Transfer APIs (Lift & Shift) | F18: 1 | G18: 0 | H18: 0 | I18: 0.25 | J18: 1 | K18: 1.5 | L18: =(D18*F18*I18+D18*G18*J18+D18*H18*K18)/9 -> 59.666667 | N18: =L18*(1-M18) -> 59.666667 | O18: Use schema /DB level approach for migration
A19: I&D | B19: GCP | C19: Stored Procedure Migration from TD to Big Query | D19: 1005 | E19: BigQuery Data Transfer APIs (Lift & Shift) | F19: 1 | G19: 0 | H19: 0 | I19: 3 | J19: 4 | K19: 5 | L19: =(D19*F19*I19+D19*G19*J19+D19*H19*K19)/9 -> 335 | M19: 0.2 | N19: =L19*(1-M19) -> 268 | O19: Same logic, minimal retrofication and bug fixing if applicable , no requirements & same logic , lift & shift
A20: I&D | B20: Infa | C20: # TD to Sources (Oracle) Write-back Jobs | D20: 394 | E20: Informatica Same logic with minimal retro efforts (Lift & Shift, Reporint) | F20: 0.8 | G20: 0.15 | H20: 0.05 | I20: 3 | J20: 4 | K20: 5 | L20: =(D20*F20*I20+D20*G20*J20+D20*H20*K20)/9 -> 142.27778 | M20: 0.2 | N20: =L20*(1-M20) -> 113.82222 | O20: Same logic, minimal retrofication and bug fixing if applicable , no requirements & same logic , lift & shift
A21: I&D | B21: GCP | C21: # Cloud Storage buckets & archival Scripts | D21: 50 | E21: Same logic with minimal retrofication & change targets | F21: 0.3 | G21: 0.4 | H21: 0.3 | I21: 0.5 | J21: 1 | K21: 2 | L21: =(D21*F21*I21+D21*G21*J21+D21*H21*K21)/9 -> 6.3888889 | N21: =L21*(1-M21) -> 6.3888889 | O21: No code change, only change connection , retrofication & smoke test
A22: I&D | B22: Spot | C22: # of Reports reporting efforts (SPOT fire) | D22: 2484 | E22: Change Source Connections & Minimal retrofications with smoke test | F22: 0.8 | G22: 0.15 | H22: 0.05 | I22: 3 | J22: 4 | K22: 5 | L22: =(D22*F22*I22+D22*G22*J22+D22*H22*K22)/9 -> 897 | N22: =L22*(1-M22) -> 897 | O22: No code change, only change connection & smoke test
A23: I&D | B23: BO | C23: # of Reports reporting efforts (SAP BO) | D23: 1039 | E23: Smoke test only & minor bug fix if any | F23: 0.8 | G23: 0.15 | H23: 0.05 | I23: 3 | J23: 4 | K23: 5 | L23: =(D23*F23*I23+D23*G23*J23+D23*H23*K23)/9 -> 375.19444 | M23: 0.3 | N23: =L23*(1-M23) -> 262.63611 | O23: No code change, only change connection, smoke test & minor bug fix if any
A24: I&D | B24: BO | C24: # of Universe Reports reporting efforts (SAP BO) | D24: 89 | E24: Change Source Connections & Minimal retrofications with smoke test(no major changes in the code , lift & shift) | F24: 0.8 | G24: 0.15 | H24: 0.05 | I24: 3 | J24: 4 | K24: 5 | L24: =(D24*F24*I24+D24*G24*J24+D24*H24*K24)/9 -> 32.138889 | M24: 0.3 | N24: =L24*(1-M24) -> 22.497222 | O24: Will be done at universe level, no major code changes, only retro & smoke test in scope, no reqirements
A25: I&D | B25: Qlik/Tab | C25: # of Reports reporting efforts (Tableau) | D25: 8 | E25: ? | F25: 0.3 | G25: 0.4 | H25: 0.3 | L25: =(D25*F25*I25+D25*G25*J25+D25*H25*K25)/9 -> 0 | M25: ?
A26: I&D | B26: Qlik/Tab | C26: # of Reports reporting efforts (QlikView) | D26: 32 | E26: ? | F26: 0.3 | G26: 0.4 | H26: 0.3 | L26: =(D26*F26*I26+D26*G26*J26+D26*H26*K26)/9 -> 0 | M26: ?
A27: I&D | B27: Qlik/Tab | C27: # of Reports reporting efforts (Composite) | D27: 1 | E27: ? | F27: 0.3 | G27: 0.4 | H27: 0.3 | L27: =(D27*F27*I27+D27*G27*J27+D27*H27*K27)/9 -> 0 | M27: ?
A28: I&D | B28: Qlik/Tab | C28: # of Reports reporting efforts (P&T) | D28: 3 | E28: ? | F28: 0.3 | G28: 0.4 | H28: 0.3 | L28: =(D28*F28*I28+D28*G28*J28+D28*H28*K28)/9 -> 0 | M28: ?
A29: DCX | B29: SF | C29: API Integration Framework-Salesforce-Cast Iron | D29: 230 | E29: ? | F29: 0.3 | G29: 0.4 | H29: 0.3 | L29: =(D29*F29*I29+D29*G29*J29+D29*H29*K29)/9 -> 0 | M29: ?
A30: I&D | B30: GCP | C30: RDM UI Build, RDM Cloud SQL Server to GBQ automated data refresh | D30: 2654 | E30: Creation GCP Data Pipes with like to like funcationality | F30: 0.3 | G30: 0.4 | H30: 0.3 | I30: 2 | J30: 3 | K30: 4 | L30: =(D30*F30*I30+D30*G30*J30+D30*H30*K30)/9 -> 884.66667 | M30: 0.2 | N30: =L30*(1-M30) -> 707.73333 | O30: Mimic existing fucntionality with no requirements
A31: I&D | B31: GCP | C31: Scheduling & Orchestration Scripts | D31: 6039 | E31: Mimic existing sheduler with Google Cloud Scheduler | F31: 0.5 | G31: 0.5 | H31: 0 | I31: 0.1 | J31: 0.2 | K31: 0.5 | L31: =(D31*F31*I31+D31*G31*J31+D31*H31*K31)/9 -> 100.65 | M31: 0.3 | N31: =L31*(1-M31) -> 70.455 | O31: No requirements only to re-use & mimic existing sheduler logic
L36: Without Savings | M36: With Savings
K37: ~FTEs | L37: =SUM(L15:L31)/(16*20) -> 20.327448 | M37: =SUM(N15:N31)/(16*20) -> 13.262811
L38: % Savings | M38: =(L37-M37)/M37 -> 0.53266516

Sheet Estimator 3 RL
G1: =SUM(G4:G123) -> 6.25 | H1: =SUM(H4:H123) -> 26 | I1: =SUM(I4:I123) -> 47.5 | J1: =SUM(J4:J123) -> 78 | K1: =SUM(K4:K123) -> 97 | L1: =SUM(L4:L123) -> 99 | M1: =SUM(M4:M123) -> 98 | N1: =SUM(N4:N123) -> 98 | ... AC1: =SUM(AC4:AC123) -> 35610.75
G2: May | H2: Jun | I2: Jul | J2: Aug | K2: Sep | L2: Oct | M2: Nov | N2: Dec | O2: Jan | P2: Feb | Q2: Mar | R2: Apr | S2: May | T2: Jun | U2: Jul | V2: Aug | W2: Sep | X2: Oct | Y2: Nov | Z2: Dec | AA2: Jan
A3: BU | B3: Team | C3: Role | D3: Local Grade | E3: Global Grade | F3: Shore | G3: M1 | H3: M2 | I3: M3 | J3: M4 | K3: M5 | L3: M6 | M3: M7 | N3: M8 | O3: M9 | P3: M10 | Q3: M11 | R3: M12 | S3: M13 | T3: M14 | U3: M15 | V3: M16 | W3: M17 | X3: M18 | Y3: M19 | Z3: M20 | AA3: M21 | AB3: Total Months | AC3: Total Efforts
A4: NA I&D | B4: Governance | C4: Engagement Lead | D4: D | E4: D2 | F4: US | G4: 1 | H4: 1 | I4: 1 | J4: 1 | K4: 1 | L4: 1 | M4: 1 | N4: 1 | O4: 1 | P4: 1 | Q4: 1 | R4: 1 | S4: 1 | T4: 1 | U4: 1 | V4: 1 | W4: 1 | X4: 1 | Y4: 1 | Z4: 1 | AA4: 0.5 | AB4: =SUM(G4:AA4) -> 20.5 | AC4: =AB4*21 -> 430.5
A5: GCP | B5: Governance | C5: Offshore Delivery Lead | D5: E | E5: E1 | F5: India | G5: 1 | H5: 1 | I5: 1 | J5: 1 | K5: 1 | L5: 1 | M5: 1 | N5: 1 | O5: 1 | P5: 1 | Q5: 1 | R5: 1 | S5: 1 | T5: 1 | U5: 1 | V5: 1 | W5: 1 | X5: 1 | Y5: 1 | Z5: 1 | AA5: 0.5 | AB5: =SUM(G5:AA5) -> 20.5 | AC5: =AB5*21 -> 430.5
A6: NA I&D | B6: Architecture | C6: Data Architect | D6: C | E6: C2 | F6: US | G6: 1 | H6: 1 | I6: 1 | J6: 1 | K6: 1 | L6: 1 | M6: 1 | N6: 1 | O6: 1 | P6: 1 | Q6: 1 | R6: 1 | S6: 1 | T6: 1 | U6: 1 | V6: 1 | W6: 1 | X6: 1 | Y6: 1 | Z6: 1 | AB6: =SUM(G6:AA6) -> 20 | AC6: =AB6*21 -> 420
A7: GCP | B7: Architecture | C7: Solution Architect | D7: D | E7: D2 | F7: India | G7: 1 | H7: 1 | I7: 1 | J7: 1 | K7: 1 | L7: 1 | M7: 1 | N7: 1 | O7: 1 | P7: 1 | Q7: 1 | R7: 1 | S7: 1 | T7: 1 | U7: 1 | V7: 1 | W7: 1 | X7: 1 | Y7: 1 | Z7: 1 | AA7: 1 | AB7: =SUM(G7:AA7) -> 21 | AC7: =AB7*21 -> 441
A8: NA I&D | B8: Architecture | C8: Platform/Cloud Architect | D8: C | E8: C2 | F8: US | G8: 0.75 | H8: 1 | I8: 1 | J8: 1 | AB8: =SUM(G8:AA8) -> 3.75 | AC8: =AB8*21 -> 78.75
A9: GCP | B9: Architecture | C9: Platform/Cloud Architect | D9: D | E9: D1 | F9: India | G9: 1 | H9: 1 | I9: 1 | J9: 1 | K9: 1 | L9: 1 | M9: 1 | N9: 1 | O9: 1 | P9: 1 | Q9: 1 | R9: 1 | S9: 1 | T9: 1 | U9: 1 | V9: 1 | W9: 1 | X9: 1 | Y9: 1 | Z9: 1 | AB9: =SUM(G9:AA9) -> 20 | AC9: =AB9*21 -> 420
A10: Testing | B10: Quality Assurance | C10: QA Lead | D10: C | E10: C2 | F10: US | H10: 1 | I10: 1 | J10: 1 | K10: 1 | L10: 1 | M10: 1 | N10: 1 | O10: 1 | P10: 1 | Q10: 1 | R10: 1 | S10: 1 | T10: 1 | U10: 1 | V10: 1 | W10: 1 | X10: 1 | Y10: 1 | Z10: 1 | AB10: =SUM(G10:AA10) -> 19 | AC10: =AB10*21 -> 399
A11: NA I&D | B11: Requrements | C11: Lead Analyst | D11: C | E11: C1 | F11: US | H11: 1 | I11: 1 | J11: 1 | K11: 1 | L11: 1 | M11: 1 | N11: 1 | O11: 1 | P11: 1 | Q11: 1 | R11: 1 | S11: 1 | T11: 1 | U11: 1 | V11: 1 | W11: 1 | X11: 1 | Y11: 1 | Z11: 1 | AB11: =SUM(G11:AA11) -> 19 | AC11: =AB11*21 -> 399
A12: NA I&D | B12: Requrements | C12: Data Analyst 1 | D12: B | E12: B2 | F12: US | H12: 1 | I12: 1 | J12: 1 | K12: 1 | L12: 1 | M12: 1 | N12: 1 | O12: 1 | P12: 1 | Q12: 1 | R12: 1 | S12: 1 | T12: 1 | U12: 1 | V12: 1 | W12: 1 | X12: 1 | Y12: 1 | Z12: 1 | AA12: 1 | AB12: =SUM(G12:AA12) -> 20 | AC12: =AB12*21 -> 420
A13: GCP | B13: Requrements | C13: Data Analyst 2 | D13: B | E13: B2 | F13: India | H13: 1 | I13: 1 | J13: 1 | K13: 1 | L13: 1 | M13: 1 | N13: 1 | O13: 1 | P13: 1 | Q13: 1 | R13: 1 | S13: 1 | T13: 1 | U13: 1 | V13: 1 | W13: 1 | X13: 1 | Y13: 1 | Z13: 1 | AB13: =SUM(G13:AA13) -> 19 | AC13: =AB13*21 -> 399
A14: GCP | B14: Requrements | C14: Data Analyst 3 | D14: B | E14: B1 | F14: India | H14: 1 | I14: 1 | J14: 1 | K14: 1 | L14: 1 | M14: 1 | N14: 1 | O14: 1 | P14: 1 | Q14: 1 | R14: 1 | S14: 1 | T14: 1 | U14: 1 | V14: 1 | W14: 1 | X14: 1 | Y14: 1 | Z14: 1 | AA14: 1 | AB14: =SUM(G14:AA14) -> 20 | AC14: =AB14*21 -> 420
A15: GCP | B15: Platform & DevOps | C15: DevOps SME | D15: C | E15: C1 | F15: India | H15: 0.5 | I15: 1 | J15: 1 | K15: 1 | L15: 1 | M15: 1 | N15: 1 | O15: 1 | P15: 1 | Q15: 1 | R15: 1 | S15: 1 | T15: 1 | U15: 1 | V15: 1 | W15: 1 | X15: 1 | Y15: 1 | Z15: 1 | AB15: =SUM(G15:AA15) -> 18.5 | AC15: =AB15*21 -> 388.5
A16: IDEA | B16: Platform & DevOps | C16: IDEA SME | D16: E | E16: E1 | F16: India | H16: 1 | I16: 1 | J16: 1 | K16: 1 | L16: 1 | M16: 1 | N16: 1 | O16: 1 | P16: 1 | Q16: 1 | R16: 1 | S16: 1 | AB16: =SUM(G16:AA16) -> 12 | AC16: =AB16*21 -> 252
A17: IDEA | B17: Platform & DevOps | C17: IDEA SME | D17: B | E17: B2 | F17: India | H17: 1 | I17: 1 | J17: 1 | K17: 1 | L17: 1 | M17: 1 | N17: 1 | O17: 1 | P17: 1 | Q17: 1 | R17: 1 | S17: 1 | T17: 1 | U17: 1 | V17: 1 | W17: 1 | X17: 1 | Y17: 1 | Z17: 1 | AB17: =SUM(G17:AA17) -> 19 | AC17: =AB17*21 -> 399
A18: NA I&D | B18: Reverse Engineering | C18: ETL SME (Inf + TD) | D18: C | E18: C1 | F18: US | G18: 0.5 | H18: 1 | I18: 1 | J18: 1 | K18: 1 | L18: 1 | M18: 1 | N18: 1 | O18: 1 | P18: 1 | Q18: 1 | R18: 1 | S18: 1 | T18: 1 | U18: 1 | V18: 1 | W18: 1 | AB18: =SUM(G18:AA18) -> 16.5 | AC18: =AB18*21 -> 346.5
A19: EDE | B19: Reverse Engineering | C19: Teradata SME | D19: C | E19: C2 | F19: India | H19: 1 | I19: 1 | J19: 1 | K19: 1 | L19: 1 | M19: 1 | N19: 1 | O19: 1 | P19: 1 | Q19: 1 | R19: 1 | S19: 1 | T19: 1 | U19: 1 | V19: 1 | W19: 1 | X19: 1 | Y19: 1 | Z19: 1 | AB19: =SUM(G19:AA19) -> 19 | AC19: =AB19*21 -> 399
A20: EDE | B20: Reverse Engineering | C20: Informatica SME | D20: C | E20: C1 | F20: India | H20: 1 | I20: 1 | J20: 1 | K20: 1 | L20: 1 | M20: 1 | N20: 1 | O20: 1 | P20: 1 | Q20: 1 | R20: 1 | S20: 1 | T20: 1 | U20: 1 | V20: 1 | W20: 1 | AB20: =SUM(G20:AA20) -> 16 | AC20: =AB20*21 -> 336
A21: EDE | B21: Reverse Engineering | C21: Informatica SME | D21: B | E21: B1 | F21: India | H21: 1 | I21: 1 | J21: 1 | K21: 1 | L21: 1 | M21: 1 | N21: 1 | O21: 1 | P21: 1 | Q21: 1 | R21: 1 | S21: 1 | T21: 1 | U21: 1 | V21: 1 | W21: 1 | X21: 1 | Y21: 1 | Z21: 1 | AB21: =SUM(G21:AA21) -> 19 | AC21: =AB21*21 -> 399
A22: GCP | B22: Schema Migration | C22: Schema Migration Lead | D22: C | E22: C2 | F22: India | H22: 0.5 | I22: 1 | J22: 1 | K22: 1 | L22: 1 | M22: 1 | N22: 1 | O22: 1 | P22: 1 | Q22: 1 | R22: 1 | S22: 1 | T22: 1 | U22: 1 | V22: 1 | W22: 1 | X22: 1 | Y22: 1 | Z22: 1 | AB22: =SUM(G22:AA22) -> 18.5 | AC22: =AB22*21 -> 388.5
A23: GCP | B23: Schema Migration | C23: Developer (GCP) | D23: B | E23: B2 | F23: India | I23: 1 | J23: 1 | K23: 1 | L23: 1 | M23: 1 | N23: 1 | O23: 1 | P23: 1 | Q23: 1 | R23: 1 | S23: 1 | T23: 1 | U23: 1 | V23: 1 | W23: 1 | X23: 1 | Y23: 1 | Z23: 1 | AB23: =SUM(G23:AA23) -> 18 | AC23: =AB23*21 -> 378
A24: GCP | B24: Schema Migration | C24: Developer (GCP) | D24: A | E24: A5 | F24: India | I24: 0.5 | J24: 1 | K24: 1 | L24: 1 | M24: 1 | N24: 1 | O24: 1 | P24: 1 | Q24: 1 | R24: 1 | S24: 1 | T24: 1 | U24: 1 | V24: 1 | W24: 1 | X24: 1 | Y24: 1 | Z24: 1 | AB24: =SUM(G24:AA24) -> 17.5 | AC24: =AB24*21 -> 367.5
A25: GCP | B25: Data Migration 1 | C25: Data Migration Lead | D25: C | E25: C2 | F25: India | H25: 0.5 | I25: 1 | J25: 1 | K25: 1 | L25: 1 | M25: 1 | N25: 1 | O25: 1 | P25: 1 | Q25: 1 | R25: 1 | S25: 1 | T25: 1 | U25: 1 | V25: 1 | W25: 1 | X25: 1 | Y25: 1 | Z25: 1 | AA25: 1 | AB25: =SUM(G25:AA25) -> 19.5 | AC25: =AB25*21 -> 409.5
A26: NA I&D | B26: Data Migration 1 | C26: Developer (GCP) | D26: B | E26: B2 | F26: US | H26: 0.5 | I26: 1 | J26: 1 | K26: 1 | L26: 1 | M26: 1 | N26: 1 | O26: 1 | P26: 1 | Q26: 1 | R26: 1 | S26: 1 | T26: 1 | U26: 1 | V26: 1 | W26: 1 | X26: 1 | Y26: 1 | Z26: 1 | AA26: 1 | AB26: =SUM(G26:AA26) -> 19.5 | AC26: =AB26*21 -> 409.5
A27: GCP | B27: Data Migration 1 | C27: Developer (GCP)/ Tester | D27: B | E27: B1 | F27: India | H27: 0.5 | I27: 2 | J27: 3 | K27: 3 | L27: 3 | M27: 3 | N27: 3 | O27: 3 | P27: 3 | Q27: 3 | R27: 3 | S27: 3 | T27: 3 | U27: 3 | V27: 3 | W27: 3 | X27: 3 | Y27: 3 | Z27: 2 | AA27: 1 | AB27: =SUM(G27:AA27) -> 53.5 | AC27: =AB27*21 -> 1123.5
A28: GCP | B28: Data Migration 1 | C28: Developer (GCP) | D28: A | E28: A5 | F28: India | H28: 0.5 | I28: 1 | J28: 2 | K28: 2 | L28: 2 | M28: 2 | N28: 2 | O28: 2 | P28: 2 | Q28: 2 | R28: 2 | S28: 2 | T28: 2 | U28: 2 | V28: 2 | W28: 2 | X28: 2 | Y28: 2 | Z28: 1 | AA28: 1 | AB28: =SUM(G28:AA28) -> 35.5 | AC28: =AB28*21 -> 745.5
A29: GCP | B29: Data Migration 2 | C29: Data Migration Lead | D29: C | E29: C1 | F29: India | I29: 0.5 | J29: 1 | K29: 1 | L29: 1 | M29: 1 | N29: 1 | O29: 1 | P29: 1 | Q29: 1 | R29: 1 | S29: 1 | T29: 1 | U29: 1 | V29: 1 | W29: 1 | X29: 1 | Y29: 1 | Z29: 1 | AA29: 1 | AB29: =SUM(G29:AA29) -> 18.5 | AC29: =AB29*21 -> 388.5
A30: NA I&D | B30: Data Migration 2 | C30: Developer (GCP) | D30: B | E30: B2 | F30: US | I30: 0.5 | J30: 1 | K30: 1 | L30: 1 | M30: 1 | N30: 1 | O30: 1 | P30: 1 | Q30: 1 | R30: 1 | S30: 1 | T30: 1 | U30: 1 | V30: 1 | W30: 1 | X30: 1 | Y30: 1 | Z30: 1 | AA30: 1 | AB30: =SUM(G30:AA30) -> 18.5 | AC30: =AB30*21 -> 388.5
A31: GCP | B31: Data Migration 2 | C31: Developer (GCP)/ Tester | D31: B | E31: B1 | F31: India | I31: 0.5 | J31: 2 | K31: 3 | L31: 3 | M31: 3 | N31: 3 | O31: 3 | P31: 3 | Q31: 3 | R31: 3 | S31: 3 | T31: 3 | U31: 3 | V31: 3 | W31: 3 | X31: 3 | Y31: 3 | Z31: 2 | AA31: 1 | AB31: =SUM(G31:AA31) -> 50.5 | AC31: =AB31*21 -> 1060.5
A32: GCP | B32: Data Migration 2 | C32: Developer (GCP) | D32: A | E32: A5 | F32: India | I32: 0.5 | J32: 2 | K32: 2 | L32: 2 | M32: 2 | N32: 2 | O32: 2 | P32: 2 | Q32: 2 | R32: 2 | S32: 2 | T32: 2 | U32: 2 | V32: 2 | W32: 2 | X32: 2 | Y32: 2 | Z32: 1 | AA32: 1 | AB32: =SUM(G32:AA32) -> 34.5 | AC32: =AB32*21 -> 724.5
A33: GCP | B33: Data Ingestion 1 | C33: Data Ingestion Lead | D33: C | E33: C2 | F33: India | H33: 0.5 | I33: 1 | J33: 1 | K33: 1 | L33: 1 | M33: 1 | N33: 1 | O33: 1 | P33: 1 | Q33: 1 | R33: 1 | S33: 1 | T33: 1 | U33: 1 | V33: 1 | W33: 1 | X33: 1 | Y33: 1 | Z33: 1 | AA33: 1 | AB33: =SUM(G33:AA33) -> 19.5 | AC33: =AB33*21 -> 409.5
A34: GCP | B34: Data Ingestion 1 | C34: Developer (GCP) | D34: B | E34: B2 | F34: India | H34: 0.5 | I34: 1 | J34: 1 | K34: 1 | L34: 1 | M34: 1 | N34: 1 | O34: 1 | P34: 1 | Q34: 1 | R34: 1 | S34: 1 | T34: 1 | U34: 1 | V34: 1 | W34: 1 | X34: 1 | AB34: =SUM(G34:AA34) -> 16.5 | AC34: =AB34*21 -> 346.5
A35: GCP | B35: Data Ingestion 1 | C35: Developer (GCP)/ Tester | D35: B | E35: B1 | F35: India | H35: 0.5 | I35: 1.5 | J35: 3 | K35: 3 | L35: 3 | M35: 3 | N35: 3 | O35: 3 | P35: 3 | Q35: 3 | R35: 3 | S35: 3 | T35: 3 | U35: 3 | V35: 3 | W35: 2 | X35: 1 | Y35: 1 | Z35: 1 | AA35: 1 | AB35: =SUM(G35:AA35) -> 47 | AC35: =AB35*21 -> 987
A36: GCP | B36: Data Ingestion 1 | C36: Developer (GCP)/ Tester | D36: A | E36: A5 | F36: India | H36: 0.5 | I36: 1 | J36: 2 | K36: 2 | L36: 2 | M36: 2 | N36: 2 | O36: 2 | P36: 2 | Q36: 2 | R36: 2 | S36: 2 | T36: 2 | U36: 2 | V36: 2 | W36: 2 | X36: 1 | AB36: =SUM(G36:AA36) -> 30.5 | AC36: =AB36*21 -> 640.5
A37: GCP | B37: Data Ingestion 2 | C37: Data Ingestion Lead | D37: C | E37: C2 | F37: India | J37: 1 | K37: 1 | L37: 1 | M37: 1 | N37: 1 | O37: 1 | P37: 1 | Q37: 1 | R37: 1 | S37: 1 | T37: 1 | U37: 1 | V37: 1 | W37: 1 | X37: 1 | Y37: 1 | Z37: 1 | AA37: 1 | AB37: =SUM(G37:AA37) -> 18 | AC37: =AB37*21 -> 378
A38: GCP | B38: Data Ingestion 2 | C38: Developer (GCP) | D38: B | E38: B2 | F38: India | J38: 1 | K38: 1 | L38: 1 | M38: 1 | N38: 1 | O38: 1 | P38: 1 | Q38: 1 | R38: 1 | S38: 1 | T38: 1 | U38: 1 | V38: 1 | W38: 1 | X38: 1 | AB38: =SUM(G38:AA38) -> 15 | AC38: =AB38*21 -> 315
A39: GCP | B39: Data Ingestion 2 | C39: Developer (GCP)/ Tester | D39: B | E39: B1 | F39: India | J39: 1 | K39: 3 | L39: 3 | M39: 3 | N39: 3 | O39: 3 | P39: 3 | Q39: 3 | R39: 3 | S39: 3 | T39: 3 | U39: 3 | V39: 3 | W39: 2 | X39: 1 | Y39: 1 | Z39: 1 | AA39: 1 | AB39: =SUM(G39:AA39) -> 43 | AC39: =AB39*21 -> 903
A40: GCP | B40: Data Ingestion 2 | C40: Developer (GCP)/ Tester | D40: A | E40: A5 | F40: India | J40: 1 | K40: 2 | L40: 2 | M40: 2 | N40: 2 | O40: 2 | P40: 2 | Q40: 2 | R40: 2 | S40: 2 | T40: 2 | U40: 2 | V40: 2 | W40: 2 | X40: 1 | AB40: =SUM(G40:AA40) -> 28 | AC40: =AB40*21 -> 588
A41: GCP | B41: Data Distillation 1 | C41: Data Distillation Lead | D41: C | E41: C2 | F41: India | I41: 1 | J41: 1 | K41: 1 | L41: 1 | M41: 1 | N41: 1 | O41: 1 | P41: 1 | Q41: 1 | R41: 1 | S41: 1 | T41: 1 | U41: 1 | V41: 1 | W41: 1 | X41: 1 | Y41: 1 | Z41: 1 | AA41: 1 | AB41: =SUM(G41:AA41) -> 19 | AC41: =AB41*21 -> 399
A42: GCP | B42: Data Distillation 1 | C42: Developer (GCP) | D42: C | E42: C1 | F42: India | I42: 1 | J42: 1 | K42: 1 | L42: 1 | M42: 1 | N42: 1 | O42: 1 | P42: 1 | Q42: 1 | R42: 1 | S42: 1 | T42: 1 | U42: 1 | V42: 1 | W42: 1 | X42: 1 | Y42: 1 | Z42: 1 | AB42: =SUM(G42:AA42) -> 18 | AC42: =AB42*21 -> 378
A43: GCP | B43: Data Distillation 1 | C43: Developer (GCP) | D43: B | E43: B2 | F43: India | I43: 1 | J43: 2 | K43: 2 | L43: 2 | M43: 2 | N43: 2 | O43: 2 | P43: 2 | Q43: 2 | R43: 2 | S43: 2 | T43: 2 | U43: 2 | V43: 2 | W43: 2 | X43: 2 | Y43: 2 | Z43: 2 | AA43: 1 | AB43: =SUM(G43:AA43) -> 36 | AC43: =AB43*21 -> 756
A44: GCP | B44: Data Distillation 1 | C44: Developer (GCP)/ Tester | D44: B | E44: B1 | F44: India | I44: 1.5 | J44: 2.5 | K44: 3 | L44: 3 | M44: 3 | N44: 3 | O44: 3 | P44: 3 | Q44: 3 | R44: 3 | S44: 3 | T44: 3 | U44: 3 | V44: 3 | W44: 3 | X44: 3 | Y44: 3 | Z44: 2 | AA44: 1 | AB44: =SUM(G44:AA44) -> 52 | AC44: =AB44*21 -> 1092
A45: GCP | B45: Data Distillation 1 | C45: Developer (GCP)/ Tester | D45: A | E45: A5 | F45: India | I45: 1 | J45: 2 | K45: 3 | L45: 3 | M45: 3 | N45: 3 | O45: 3 | P45: 3 | Q45: 3 | R45: 3 | S45: 3 | T45: 3 | U45: 3 | V45: 3 | W45: 3 | X45: 3 | Y45: 2 | Z45: 2 | AA45: 1 | AB45: =SUM(G45:AA45) -> 50 | AC45: =AB45*21 -> 1050
A46: GCP | B46: Data Distillation 2 | C46: Data Distillation Lead | D46: C | E46: C2 | F46: India | J46: 1 | K46: 1 | L46: 1 | M46: 1 | N46: 1 | O46: 1 | P46: 1 | Q46: 1 | R46: 1 | S46: 1 | T46: 1 | U46: 1 | V46: 1 | W46: 1 | X46: 1 | Y46: 1 | Z46: 1 | AA46: 1 | AB46: =SUM(G46:AA46) -> 18 | AC46: =AB46*21 -> 378
A47: GCP | B47: Data Distillation 2 | C47: Developer (GCP) | D47: C | E47: C1 | F47: India | J47: 1 | K47: 1 | L47: 1 | M47: 1 | N47: 1 | O47: 1 | P47: 1 | Q47: 1 | R47: 1 | S47: 1 | T47: 1 | U47: 1 | V47: 1 | W47: 1 | X47: 1 | Y47: 1 | Z47: 1 | AB47: =SUM(G47:AA47) -> 17 | AC47: =AB47*21 -> 357
A48: GCP | B48: Data Distillation 2 | C48: Developer (GCP) | D48: B | E48: B2 | F48: India | J48: 1 | K48: 2 | L48: 2 | M48: 2 | N48: 2 | O48: 2 | P48: 2 | Q48: 2 | R48: 2 | S48: 2 | T48: 2 | U48: 2 | V48: 2 | W48: 2 | X48: 2 | Y48: 2 | Z48: 2 | AA48: 1 | AB48: =SUM(G48:AA48) -> 34 | AC48: =AB48*21 -> 714
A49: GCP | B49: Data Distillation 2 | C49: Developer (GCP)/ Tester | D49: B | E49: B1 | F49: India | J49: 2.5 | K49: 3 | L49: 3 | M49: 3 | N49: 3 | O49: 3 | P49: 3 | Q49: 3 | R49: 3 | S49: 3 | T49: 3 | U49: 3 | V49: 3 | W49: 3 | X49: 3 | Y49: 3 | Z49: 2 | AA49: 1 | AB49: =SUM(G49:AA49) -> 50.5 | AC49: =AB49*21 -> 1060.5
A50: GCP | B50: Data Distillation 2 | C50: Developer (GCP)/ Tester | D50: A | E50: A5 | F50: India | J50: 2 | K50: 3 | L50: 3 | M50: 3 | N50: 3 | O50: 3 | P50: 3 | Q50: 3 | R50: 3 | S50: 3 | T50: 3 | U50: 3 | V50: 3 | W50: 3 | X50: 3 | Y50: 2 | Z50: 2 | AA50: 1 | AB50: =SUM(G50:AA50) -> 49 | AC50: =AB50*21 -> 1029
A51: GCP | B51: Data Distillation 2 | C51: Data Distillation Lead | D51: C | E51: C2 | F51: India | K51: 1 | L51: 1 | M51: 1 | N51: 1 | O51: 1 | P51: 1 | Q51: 1 | R51: 1 | S51: 1 | T51: 1 | U51: 1 | V51: 1 | W51: 1 | X51: 1 | Y51: 1 | Z51: 1 | AA51: 1 | AB51: =SUM(G51:AA51) -> 17 | AC51: =AB51*21 -> 357
A52: GCP | B52: Data Distillation 3 | C52: Developer (GCP) | D52: C | E52: C1 | F52: India | K52: 1 | L52: 1 | M52: 1 | N52: 1 | O52: 1 | P52: 1 | Q52: 1 | R52: 1 | S52: 1 | T52: 1 | U52: 1 | V52: 1 | W52: 1 | X52: 1 | Y52: 1 | Z52: 1 | AB52: =SUM(G52:AA52) -> 16 | AC52: =AB52*21 -> 336
A53: GCP | B53: Data Distillation 3 | C53: Developer (GCP) | D53: B | E53: B2 | F53: India | K53: 1 | L53: 2 | M53: 2 | N53: 2 | O53: 2 | P53: 2 | Q53: 2 | R53: 2 | S53: 2 | T53: 2 | U53: 2 | V53: 2 | W53: 2 | X53: 2 | Y53: 2 | Z53: 2 | AA53: 1 | AB53: =SUM(G53:AA53) -> 32 | AC53: =AB53*21 -> 672
A54: GCP | B54: Data Distillation 3 | C54: Developer (GCP)/ Tester | D54: B | E54: B1 | F54: India | K54: 2 | L54: 3 | M54: 3 | N54: 3 | O54: 3 | P54: 3 | Q54: 3 | R54: 3 | S54: 3 | T54: 3 | U54: 3 | V54: 3 | W54: 3 | X54: 3 | Y54: 3 | Z54: 2 | AA54: 1 | AB54: =SUM(G54:AA54) -> 47 | AC54: =AB54*21 -> 987
A55: GCP | B55: Data Distillation 3 | C55: Developer (GCP)/ Tester | D55: A | E55: A5 | F55: India | K55: 2 | L55: 3 | M55: 3 | N55: 3 | O55: 3 | P55: 3 | Q55: 3 | R55: 3 | S55: 3 | T55: 3 | U55: 3 | V55: 3 | W55: 3 | X55: 3 | Y55: 2 | Z55: 2 | AA55: 1 | AB55: =SUM(G55:AA55) -> 46 | AC55: =AB55*21 -> 966
A56: DCX | B56: UI Development | C56: UI Developer/ Angular | D56: C | E56: C1 | F56: India | J56: 1 | K56: 1 | L56: 0.5 | AB56: =SUM(G56:AA56) -> 2.5 | AC56: =AB56*21 -> 52.5
A57: DCX | B57: UI Development | C57: UI Developer/ Angular | D57: B | E57: B2 | F57: India | J57: 1 | K57: 1 | L57: 0.5 | AB57: =SUM(G57:AA57) -> 2.5 | AC57: =AB57*21 -> 52.5
A58: AI&A | B58: Governance | C58: Offshore Reporting Lead | D58: C | E58: C2 | F58: India | H58: 1 | I58: 1 | J58: 1 | K58: 1 | L58: 1 | M58: 1 | N58: 1 | O58: 1 | P58: 1 | Q58: 1 | R58: 1 | S58: 1 | T58: 1 | U58: 1 | V58: 1 | W58: 1 | X58: 1 | Y58: 1 | Z58: 1 | AA58: 1 | AB58: =SUM(G58:AA58) -> 20 | AC58: =AB58*21 -> 420
A59: AI&A | B59: Report Repoint (Q/T) | C59: Report Developer | D59: C | E59: C1 | F59: India | K59: 1 | L59: 1 | M59: 1 | N59: 1 | O59: 1 | P59: 1 | Q59: 1 | R59: 1 | S59: 1 | T59: 1 | U59: 1 | V59: 1 | W59: 1 | X59: 1 | Y59: 1 | Z59: 1 | AA59: 1 | AB59: =SUM(G59:AA59) -> 17 | AC59: =AB59*21 -> 357
A60: AI&A | B60: Report Repoint (SAP) | C60: Report Developer | D60: C | E60: C1 | F60: India | I60: 1 | J60: 1 | K60: 1 | L60: 1 | M60: 1 | N60: 1 | O60: 1 | P60: 1 | Q60: 1 | R60: 1 | S60: 1 | T60: 1 | U60: 1 | V60: 1 | W60: 1 | X60: 1 | Y60: 1 | Z60: 1 | AA60: 1 | AB60: =SUM(G60:AA60) -> 19 | AC60: =AB60*21 -> 399
A61: AI&A | B61: Report Repoint (SAP) | C61: Report Developer | D61: B | E61: B2 | F61: India | I61: 1 | J61: 1 | K61: 1 | L61: 1 | M61: 1 | N61: 1 | O61: 1 | P61: 1 | Q61: 1 | R61: 1 | S61: 1 | T61: 1 | U61: 1 | V61: 1 | W61: 1 | X61: 1 | Y61: 1 | Z61: 1 | AA61: 1 | AB61: =SUM(G61:AA61) -> 19 | AC61: =AB61*21 -> 399
A62: AI&A | B62: Report Repoint (SAP) | C62: Report Developer / Tester | D62: B | E62: B1 | F62: India | J62: 1 | K62: 1 | L62: 1 | M62: 1 | N62: 1 | O62: 1 | P62: 1 | Q62: 1 | R62: 1 | S62: 1 | T62: 1 | U62: 1 | V62: 1 | W62: 1 | X62: 1 | Y62: 1 | Z62: 1 | AA62: 1 | AB62: =SUM(G62:AA62) -> 18 | AC62: =AB62*21 -> 378
A63: AI&A | B63: Report Repoint (SAP) | C63: Report Developer / Tester | D63: A | E63: A5 | F63: India | J63: 1 | K63: 2 | L63: 2 | M63: 2 | N63: 2 | O63: 2 | P63: 2 | Q63: 2 | R63: 2 | S63: 2 | T63: 2 | U63: 2 | V63: 2 | W63: 2 | X63: 2 | Y63: 2 | Z63: 1 | AA63: 1 | AB63: =SUM(G63:AA63) -> 33 | AC63: =AB63*21 -> 693
A64: AI&A | B64: Report Repoint (Tibco) | C64: Report Developer | D64: C | E64: C1 | F64: India | I64: 1 | J64: 1 | K64: 1 | L64: 1 | M64: 1 | N64: 1 | O64: 1 | P64: 1 | Q64: 1 | R64: 1 | S64: 1 | T64: 1 | U64: 1 | V64: 1 | W64: 1 | X64: 1 | Y64: 1 | Z64: 1 | AA64: 1 | AB64: =SUM(G64:AA64) -> 19 | AC64: =AB64*21 -> 399
A65: AI&A | B65: Report Repoint (Tibco) | C65: Report Developer | D65: B | E65: B2 | F65: India | I65: 1 | J65: 1 | K65: 1 | L65: 1 | M65: 1 | N65: 1 | O65: 1 | P65: 1 | Q65: 1 | R65: 1 | S65: 1 | T65: 1 | U65: 1 | V65: 1 | W65: 1 | X65: 1 | Y65: 1 | Z65: 1 | AA65: 1 | AB65: =SUM(G65:AA65) -> 19 | AC65: =AB65*21 -> 399
A66: AI&A | B66: Report Repoint (Tibco) | C66: Report Developer / Tester | D66: B | E66: B1 | F66: India | I66: 1 | J66: 2 | K66: 2 | L66: 2 | M66: 2 | N66: 2 | O66: 2 | P66: 2 | Q66: 2 | R66: 2 | S66: 2 | T66: 2 | U66: 2 | V66: 2 | W66: 2 | X66: 2 | Y66: 2 | Z66: 2 | AA66: 1 | AB66: =SUM(G66:AA66) -> 36 | AC66: =AB66*21 -> 756
A67: AI&A | B67: Report Repoint (Tibco) | C67: Report Developer / Tester | D67: A | E67: A5 | F67: India | J67: 1 | K67: 2 | L67: 2 | M67: 2 | N67: 2 | O67: 2 | P67: 2 | Q67: 2 | R67: 2 | S67: 2 | T67: 2 | U67: 2 | V67: 2 | W67: 2 | X67: 2 | Y67: 2 | Z67: 1 | AA67: 1 | AB67: =SUM(G67:AA67) -> 33 | AC67: =AB67*21 -> 693
A68: Testing | B68: Quality Assurance | C68: Test Lead | D68: C | E68: C1 | F68: India | H68: 1 | I68: 1 | J68: 1 | K68: 1 | L68: 1 | M68: 1 | N68: 1 | O68: 1 | P68: 1 | Q68: 1 | R68: 1 | S68: 1 | T68: 1 | U68: 1 | V68: 1 | W68: 1 | X68: 1 | Y68: 1 | Z68: 1 | AB68: =SUM(G68:AA68) -> 19 | AC68: =AB68*21 -> 399 | AE68: 2715 | AF68: =AE68-AD68 -> 2715
A69: Testing | B69: Quality Assurance | C69: Sr Testers | D69: B | E69: B2 | F69: India | H69: 1 | I69: 1 | J69: 1 | K69: 1 | L69: 1 | M69: 1 | N69: 1 | O69: 1 | P69: 1 | Q69: 1 | R69: 1 | S69: 1 | T69: 1 | U69: 1 | V69: 1 | W69: 1 | X69: 1 | Y69: 1 | Z69: 1 | AB69: =SUM(G69:AA69) -> 19 | AC69: =AB69*21 -> 399
A70: Testing | B70: Quality Assurance | C70: Tester | D70: B | E70: B1 | F70: India | H70: 1 | I70: 1 | J70: 1 | K70: 1 | L70: 1 | M70: 1 | N70: 1 | O70: 1 | P70: 1 | Q70: 1 | R70: 1 | S70: 1 | T70: 1 | U70: 1 | V70: 1 | W70: 1 | X70: 1 | Y70: 1 | Z70: 1 | AB70: =SUM(G70:AA70) -> 19 | AC70: =AB70*21 -> 399
A71: Testing | B71: Quality Assurance | C71: Jr Tesers | D71: A | E71: A5 | F71: India | I71: 1 | J71: 2 | K71: 4 | L71: 4 | M71: 4 | N71: 4 | O71: 4 | P71: 4 | Q71: 3 | R71: 3 | S71: 3 | T71: 3 | U71: 3 | V71: 3 | W71: 3 | X71: 3 | Y71: 3 | Z71: 1 | AB71: =SUM(G71:AA71) -> 55 | AC71: =AB71*21 -> 1155
AB72: =SUM(G72:AA72) -> 0 | AC72: =AB72*21 -> 0
AB73: =SUM(G73:AA73) -> 0 | AC73: =AB73*21 -> 0
AB74: =SUM(G74:AA74) -> 0 | AC74: =AB74*21 -> 0
AB75: =SUM(G75:AA75) -> 0 | AC75: =AB75*21 -> 0
AB76: =SUM(G76:AA76) -> 0 | AC76: =AB76*21 -> 0
AB77: =SUM(G77:AA77) -> 0 | AC77: =AB77*21 -> 0
AB78: =SUM(G78:AA78) -> 0 | AC78: =AB78*21 -> 0
AB79: =SUM(G79:AA79) -> 0 | AC79: =AB79*21 -> 0
AB80: =SUM(G80:AA80) -> 0 | AC80: =AB80*21 -> 0
AB81: =SUM(G81:AA81) -> 0 | AC81: =AB81*21 -> 0
AB82: =SUM(G82:AA82) -> 0 | AC82: =AB82*21 -> 0
AB83: =SUM(G83:AA83) -> 0 | AC83: =AB83*21 -> 0
... AB104: =SUM(G104:AA104) -> 0 | AC104: =AB104*21 -> 0

Sheet Assumptions
A1: # | B1: Assumption
A2: 1 | B2: No Data Modelling efforts required for Reporting side.
A3: 2 | B3: Connection between Cast Iron and Teradata is via REST APIs only.
A4: 3 | B4: Regarding "RDM Cloud SQL Server to GBQ automated data refresh" - Assuming 2654 tables needs to be refreshed by batch jobs. 4 tables per job. i.e. 663 jobs.
A5: 4 | B5: JDK needs to install in the enviromrnt in tomcat server BO application server and BO client tool needs to install in the same server/system for METADATA EXTRACTOR
A6: 5 | B6: BO 4.3 platform should be available before starting this project.
A7: 6 | B7: Installation,configuration and user managment of SAP BO 4.3 server is out of scope.
A8: 7 | B8: We assumed that only Teradata and GCP data sources will be in scope.
A9: 8 | B9: If redesigning of webi reports are required then extra efforts will be included.
A10: 9

Sheet SAP BO Complexity Definition
A1: GCP Artifacts Complexity Definition
A2: Object Name | B2: Simple | C2: Medium | D2: Complex
A3: Table | B3: less than 500 GB | C3: Between 500 Gb & 5 TB | D3: More than 5 TB
A4: View | B4: Referring to less than 3 tables | C4: Referring to between 3 to 6 tables | D4: Referring to more than 6 tables
A5: Stored Procedure | B5: Less than 30 lines of code | C5: Between 30 lines to 100 lines of code | D5: More than 100 lines of code
A6: Data FLow job | B6: less than 3 transformations | C6: Between 3 to 7 transformations | D6: More than 7 transformations
A7: Composer | B7: less than 5 tasks or steps | C7: Between 5 to 9 tasks or steps | D7: More than 9 tasks or steps
A9: SAP BO
A10: Universe Paramater | B10: Simple | C10: Medium | D10: Complex
A11: # of Tables/Joins | B11: < 3 | C11: 3 to 5 | D11: 5 to 10 | F11: =_xlfn.CONCAT(A11," '",D11,"'") -> # of Tables/Joins '5 to 10'
A12: No Of Fields per table | B12: <= 15 | C12: > 15 <= 30 | D12: 30 to 50 | F12: =_xlfn.CONCAT(A12," '",D12,"'") -> No Of Fields per table '30 to 50 '
A13: Avg. Data Size | B13: <=1 M | C13: >1 M <= 2M | D13: >2M <= 10M | F13: =_xlfn.CONCAT(A13," '",D13,"'") -> Avg. Data Size '>2M <= 10M '
A14: Use of Views and Stored Procedures | B14: N/A | C14: N/A | D14: <=5 | F14: =_xlfn.CONCAT(A14," '",D14,"'") -> Use of Views and Stored Procedures '<=5'
A15: Custom SQL Script | B15: 1 | C15: 1 to 2 | D15: 3 to 5 | F15: =_xlfn.CONCAT(A15," '",D15,"'") -> Custom SQL Script '3 to 5'
A16: Number of Data Sources | B16: 1 | C16: <= 3 | D16: 3 to 6 | F16: =_xlfn.CONCAT(A16," '",D16,"'") -> Number of Data Sources '3 to 6'
A17: Basic data conversion (Format, datetime conversion, currency, string operation etc…) | B17: <=5 | C17: 5 to 10 | D17: 11 to 15 | F17: =_xlfn.CONCAT(A17," '",D17,"'") -> Basic data conversion (Format, datetime conversion, currency, string operation etc…) '11 to 15 '
A18: No of KPI's | B18: <=2 | C18: >2 and <=5 | D18: 5 to 10 | F18: =_xlfn.CONCAT(A18," '",D18,"'") -> No of KPI's '5 to 10'
A19: No aggregated awareness/Index awareness | B19: N/A | C19: N/A | D19: < 2 | F19: =_xlfn.CONCAT(A19," '",D19,"'") -> No aggregated awareness/Index awareness '< 2'
A20: #Prompts/runtime parameter | B20: <=3 | C20: >3 <= 5 | D20: 6 to 10 | F20: =_xlfn.CONCAT(A20," '",D20,"'") -> #Prompts/runtime parameter '6 to 10 '
A22: Webi Report Parameter | B22: Simple | C22: Medium | D22: Complex
A23: # of Queries | B23: < 2 | C23: 2 to 4 | D23: > 4
A24: No of Objects per query | B24: <= 10 | C24: > 10 <= 20 | D24: > 20
A25: Avg. Data Size | B25: <=1 M | C25: >1 M <= 2M | D25: >2M <= 10M
A26: Use of Filters | B26: < 4 | C26: 4 to 10 | D26: > 10
A27: Custom SQL Script | B27: N/A | C27: N/A | D27: <=3
A28: Number of Data Sources | B28: N/A | C28: N/A | D28: N/A
A29: Webi Variables (Format, datetime conversion, currency, string operation etc…) | B29: <=5 | C29: 5 to 10 | D29: 11 to 15
A30: No of KPI's | B30: <=2 | C30: >2 and <=5 | D30: 5 to 10
A31: No of Tabs per report | B31: <= 2 | C31: 2 to 5 | D31: > 5
A32: #Prompts/runtime parameter | B32: <=3 | C32: >3 <= 5 | D32: 6 to 10

Sheet Estimator -3
A1: Phase | B1: Efforts | C1: % Add On | D1: Comments
A2: Project Management | B2: =($B$5/55)*(100*C2) -> 3526.8517 | C2: 0.1
A3: Analysis and Requirement Gathering | B3: =($B$5/55)*(100*C3) -> 1763.4259 | C3: 0.05 | D3: Concept Design | E3: No req, only analysis
A4: Design Efforts | B4: =($B$5/55)*(100*C4) -> 1587.0833 | C4: 0.045 | D4: Concept Design | E4: Minimal efforts to mimic existing data models
A5: Development and Unit Testing + 5% data migration | B5: =SUM(N16:N38) -> 19397.684 | C5: 0.55
A6: System(& Integration) Testing | B6: =($B$5/55)*(100*C6) -> 3632.6573 | C6: 0.103 | D6: Full load with history + Bug fixing | E6: Will be majorly done by testing team with Auto Data validation Tool + 10% of critical reports performance testing efforts
A7: Performance testing & data validation for 10% of critical reports + Data validation for all tables | B7: 2715 | C7: 0.077 | D7: Based on Bottoms estimations from Testing Team
A8: UAT | B8: =($B$5/55)*(100*C8) -> 1587.0833 | C8: 0.045
A9: Deployment | B9: =($B$5/55)*(100*C9) -> 1058.0555 | C9: 0.03 | D9: CI-CD | F9: =B11/(21*21) -> 79.972429
A10: KT & Hypercare | B10: 0 | C10: Based on schedule
A11: Total Efforts | B11: =SUM(B2:B10) -> 35267.841
F14: Complexity Matrix | I14: Cut Estimates to Build & Test in Hrs | L14: Total Efforts in PDs | M14: % Savings (Reusability/ Tools/ Automations) | N14: PD post Savings | O14: Comments
A15: BU | B15: SL | C15: Object Type | D15: # Objects/ Jobs | E15: Method of Migration | F15: Simple | G15: Mid | H15: Complex | I15: Simple | J15: Mid | K15: Complex
A16: I&D | B16: GCP | C16: No. Of Tables / Files | D16: 15724 | E16: Mimic same logic using TD2BQ converter. Considered 60% simple 1 to 1 for data ingestion jobs | F16: 0.6 | G16: 0.3 | H16: 0.1 | I16: 0.5 | J16: 1.5 | K16: 2 | L16: =(D16*F16*I16+D16*G16*J16+D16*H16*K16)/9 -> 1659.7556 | M16: 0.7 | N16: =L16*(1-M16) -> 497.92667 | O16: Source to STG Simple jobs with Parameterized scripts 35% ; Transpiler & Universal Universal Migrator for Shema conversions 40% ;5% productivity with repeating task | P16: =N16/D16 -> 0.031666667
A17: I&D | B17: GCP | C17: # of Views, Semantic Layer | D17: 25992 | E17: Mimic same logic using TD2BQ converter | F17: 0.5 | G17: 0.4 | H17: 0.1 | I17: 1 | J17: 2 | K17: 3 | L17: =(D17*F17*I17+D17*G17*J17+D17*H17*K17)/9 -> 4620.8 | M17: 0.5 | N17: =L17*(1-M17) -> 2310.4 | O17: Transpiler & Universal Universal Migrator for Shema conversions 45% ;5% productivity with repeating task | P17: =N17/D17 -> 0.088888889
A18: I&D | B18: GCP | C18: # of ETL views with business Logic | D18: 4052 | E18: Mimic same logic using Google Data Pipelines & GBQs. | F18: 0.3 | G18: 0.4 | H18: 0.3 | I18: 8 | J18: 12 | K18: 18 | L18: =(D18*F18*I18+D18*G18*J18+D18*H18*K18)/9 -> 5672.8 | M18: 0.1 | N18: =L18*(1-M18) -> 5105.52 | O18: 5% savings with no requirements ; 2-3 % savings with parameterized common codes ; 1-3% from productivity from repeating tasks(e.g. CI-CD FM, Audit FM, Recon FM etc..) | P18: =N18/D18 -> 1.26
A19: I&D | B19: GCP | C19: Informatica Transformation in GBQ SP | D19: 2148 | E19: Mimic same logic using Google Data Pipelines & GBQs | F19: 0.3 | G19: 0.4 | H19: 0.3 | I19: 8 | J19: 16 | K19: 24 | L19: =(D19*F19*I19+D19*G19*J19+D19*H19*K19)/9 -> 3818.6667 | M19: 0.1 | N19: =L19*(1-M19) -> 3436.8 | O19: 5% savings with no requirements ; 2-3 % savings with parameterized common codes ; 1-3% from productivity from repeating tasks(e.g. CI-CD FM, audit FM, Recon FM etc..) | P19: =N19/D19 -> 1.6
A20: I&D | B20: GCP | C20: Stored Procedure Migration from TD to Big Query | D20: 1005 | E20: Mimic same logic using Google Data Pipelines & GBQs | F20: 0.6 | G20: 0.3 | H20: 0.1 | I20: 2 | J20: 5 | K20: 8 | L20: =(D20*F20*I20+D20*G20*J20+D20*H20*K20)/9 -> 390.83333 | M20: 0.5 | N20: =L20*(1-M20) -> 195.41667 | O20: Transpiler & Universal Universal Migrator for Shema conversions 45% ;5% productivity with repeating task | P20: =N20/D20 -> 0.19444444
A21: I&D | B21: GCP | C21: # TD to Sources (Oracle) Write-back Jobs | D21: 394 | E21: Mimic same logic using Google Data Pipelines & GBQs | F21: 0.3 | G21: 0.4 | H21: 0.3 | I21: 16 | J21: 24 | K21: 32 | L21: =(D21*F21*I21+D21*G21*J21+D21*H21*K21)/9 -> 1050.6667 | M21: 0.7 | N21: =L21*(1-M21) -> 315.2 | O21: Reused Access to Oracle scripts with retrofitting source connections with Big Query with same targets 60% ; 10% productivity with parameterizing connections | P21: =N21/D21 -> 0.8
A22: I&D | B22: GCP | C22: # Cloud Storage buckets & archival Scripts | D22: 50 | E22: Same logic with minimal Retrofitting & change targets | F22: 0.3 | G22: 0.4 | H22: 0.3 | I22: 8 | J22: 16 | K22: 24 | L22: =(D22*F22*I22+D22*G22*J22+D22*H22*K22)/9 -> 88.888889 | M22: 0.7 | N22: =L22*(1-M22) -> 26.666667 | O22: Reused BIG Query to Oracle scripts with retrofitting source connections with Big Query with same targets 60% ; 10% productivity with parameterizing connections | P22: =N22/D22 -> 0.53333333
A23: I&D | B23: GCP | C23: RDM Cloud SQL Server to GBQ automated data refresh | D23: 663 | E23: Creation GCP Data Pipes with like to like functionality | F23: 0.3 | G23: 0.4 | H23: 0.3 | I23: 12 | J23: 16 | K23: 32 | L23: =(D23*F23*I23+D23*G23*J23+D23*H23*K23)/9 -> 1443.8667 | M23: 0.35 | N23: =L23*(1-M23) -> 938.51333 | O23: Reuse same population logic for Reference data uploads from files to STG with target connection changes and retrofitting with ~35% of savings | P23: =N23/D23 -> 1.4155556
A24: I&D | B24: GCP | C24: RDM UI Build | D24: 1 | E24: Create UI to enable business to upload reference data | F24: 0 | G24: 1 | H24: 0 | I24: 40 | J24: 80 | K24: 100 | L24: =(D24*F24*I24+D24*G24*J24+D24*H24*K24)/9 -> 8.8888889 | M24: 0 | N24: =L24*(1-M24) -> 8.8888889 | O24: Need to build with the same logic on new platform & new targets | P24: =N24/D24 -> 8.8888889
A25: I&D | B25: GCP | C25: Scheduling & Orchestration Scripts | D25: 6039 | E25: Mimic existing scheduler with Google Cloud Scheduler /Composer | F25: 0.3 | G25: 0.4 | H25: 0.3 | I25: 8 | J25: 16 | K25: 24 | L25: =(D25*F25*I25+D25*G25*J25+D25*H25*K25)/9 -> 10736 | M25: 0.5 | N25: =L25*(1-M25) -> 5368 | O25: Mimic same logic in Cloud Composer to achieve functionality ; reverse engineering with same logic with 30% savings; 10% savings with parametrizing simple jobs | P25: =N25/D25 -> 0.88888889
A26: I&D | B26: Spot | C26: # of Reports reporting efforts (SPOT fire) | D26: 2484 | E26: Change Source Connections & Minimal Retrofitting with smoke test | F26: 0.3 | G26: 0.4 | H26: 0.3 | I26: 2 | J26: 4 | K26: 6 | L26: =(D26*F26*I26+D26*G26*J26+D26*H26*K26)/9 -> 1104 | M26: 0.4 | N26: =L26*(1-M26) -> 662.4 | O26: Spotfire data connectors for at metadata level & replacing scripts with connection information will save ~30% savings; productivity with repeating tasks ~8-10% | P26: =N26/D26 -> 0.26666667
A27: I&D | B27: BO | C27: # of Reports reporting efforts (SAP BO) | D27: 1039 | E27: Change Source Connections & Minimal Retrofitting with smoke test | F27: 0.5 | G27: 0.3 | H27: 0.2 | I27: 2 | J27: 3 | K27: 4 | L27: =(D27*F27*I27+D27*G27*J27+D27*H27*K27)/9 -> 311.7 | M27: 0.1 | N27: =L27*(1-M27) -> 280.53 | O27: Metadata Extractor & replacing required changes in the meta codes ~8-10 % savings | P27: =N27/D27 -> 0.27
A28: I&D | B28: BO | C28: # of Universe Reports reporting efforts (SAP BO) | D28: 89 | E28: Change Source Connections & Minimal Retrofitting with smoke test | F28: 0 | G28: 0.6 | H28: 0.4 | I28: 0 | J28: 25 | K28: 35 | L28: =(D28*F28*I28+D28*G28*J28+D28*H28*K28)/9 -> 286.77778 | M28: 0.4 | N28: =L28*(1-M28) -> 172.06667 | O28: Changing the connection @ Universe level & retrofitting common replacements using metadata extractor ~30% savings ; productivity with repeating tasks ~8-10% | P28: =N28/D28 -> 1.9333333
A29: I&D | B29: Qlik/Tab | C29: # of Reports reporting efforts (Tableau) | D29: 8 | E29: Change Source Connections & Minimal Retrofitting with smoke test | F29: 0.3 | G29: 0.4 | H29: 0.3 | I29: 2 | J29: 4 | K29: 6 | L29: =(D29*F29*I29+D29*G29*J29+D29*H29*K29)/9 -> 3.5555556 | M29: 0 | N29: =L29*(1-M29) -> 3.5555556 | P29: =N29/D29 -> 0.44444444
A30: I&D | B30: Qlik/Tab | C30: # of Reports reporting efforts (QlikView) | D30: 32 | E30: Change Source Connections & Minimal Retrofitting with smoke test | F30: 0.3 | G30: 0.4 | H30: 0.3 | I30: 2 | J30: 4 | K30: 6 | L30: =(D30*F30*I30+D30*G30*J30+D30*H30*K30)/9 -> 14.222222 | M30: 0 | N30: =L30*(1-M30) -> 14.222222 | P30: =N30/D30 -> 0.44444444
A31: I&D | B31: Qlik/Tab | C31: # of Reports reporting efforts (Composite) | D31: 1 | E31: Change Source Connections & Minimal Retrofitting with smoke test | F31: 0.3 | G31: 0.4 | H31: 0.3 | I31: 2 | J31: 4 | K31: 6 | L31: =(D31*F31*I31+D31*G31*J31+D31*H31*K31)/9 -> 0.44444444 | M31: 0 | N31: =L31*(1-M31) -> 0.44444444 | P31: =N31/D31 -> 0.44444444
A32: I&D | B32: Qlik/Tab | C32: # of Reports reporting efforts (P&T) | D32: 3 | E32: Change Source Connections & Minimal Retrofitting with smoke test | F32: 0.3 | G32: 0.4 | H32: 0.3 | I32: 2 | J32: 4 | K32: 6 | L32: =(D32*F32*I32+D32*G32*J32+D32*H32*K32)/9 -> 1.3333333 | M32: 0 | N32: =L32*(1-M32) -> 1.3333333 | P32: =N32/D32 -> 0.44444444
A33: I&D | B33: GCP | C33: API Integration Framework-Salesforce-Cast Iron | D33: 230 | E33: Same logic with minimal Retrofitting &retrofitting efforts for consumption | F33: 0.3 | G33: 0.4 | H33: 0.3 | I33: 1 | J33: 3 | K33: 8 | L33: =(D33*F33*I33+D33*G33*J33+D33*H33*K33)/9 -> 99.666667 | M33: 0.4 | N33: =L33*(1-M33) -> 59.8 | O33: Reuse same population logic from Access to Cast Iron Data Hub with replacing source & retrofit minor changes ~40 % savings | P33: =N33/D33 -> 0.26
A34: I&D | B34: BO | C34: Move SAP BO on GCP with lift & Shift (Dev/Prod/QA) & Authentication | D34: 0 | E34: Lift & Shift on GCP Virtual Machines/ MP | F34: 0 | G34: 1 | H34: 0 | I34: 50 | J34: 100 | K34: 150 | L34: =(D34*F34*I34+D34*G34*J34+D34*H34*K34)/9 -> 0 | M34: 0 | N34: =L34*(1-M34) -> 0 | O34: Lift & Shift Platform Migration on GCP
A35: I&D | B35: Spot | C35: Move Spotfire on GCP with lift & Shift (Dev/Prod/QA) & Authentication | D35: 0 | E35: Lift & Shift on GCP Virtual Machines/ MP | F35: 0 | G35: 1 | H35: 0 | I35: 50 | J35: 100 | K35: 150 | L35: =(D35*F35*I35+D35*G35*J35+D35*H35*K35)/9 -> 0 | M35: 0 | N35: =L35*(1-M35) -> 0
A36: I&D | B36: Qlik/Tab | C36: Move Tableau on GCP with lift & Shift (Dev/Prod/QA) & Authentication | D36: 0 | E36: Lift & Shift on GCP Virtual Machines/ MP | F36: 0 | G36: 1 | H36: 0 | I36: 50 | J36: 100 | K36: 150 | L36: =(D36*F36*I36+D36*G36*J36+D36*H36*K36)/9 -> 0 | M36: 0 | N36: =L36*(1-M36) -> 0
A37: I&D | B37: Qlik/Tab | C37: Move QlikView on GCP with lift & Shift (Dev/Prod/QA) & Authentication | D37: 0 | E37: Lift & Shift on GCP Virtual Machines/ MP | F37: 0 | G37: 1 | H37: 0 | I37: 50 | J37: 100 | K37: 150 | L37: =(D37*F37*I37+D37*G37*J37+D37*H37*K37)/9 -> 0 | M37: 0 | N37: =L37*(1-M37) -> 0
A38: I&D | B38: GCP | C38: Move Cast Iron (Sales Force) with lift & Shift (Dev/Prod/QA) & Authentication | D38: 0 | E38: Lift & Shift on GCP Virtual Machines/ MP | F38: 0 | G38: 1 | H38: 0 | I38: 50 | J38: 100 | K38: 150 | L38: =(D38*F38*I38+D38*G38*J38+D38*H38*K38)/9 -> 0 | M38: 0 | N38: =L38*(1-M38) -> 0
L40: Without Savings | M40: With Savings
K41: Man-days | L41: =SUM(L16:L38) -> 31312.867 | M41: =SUM(N16:N38) -> 19397.684
L42: % Savings | M42: =(L41-M41)/L41 -> 0.38052033

Sheet Jobs by Layer
C1: 0.6 | D1: 0.4
A2: Objects | B2: Counts | C2: Ingestion | D2: Data | E2: Schema | F2: Code | G2: Layer | H2: Comments
A3: No. Of Tables / Files | B3: 15724
A4: No. Of Tables / Files STG 60% | B4: =B3*0.6 -> 9434.4 | C4: Yes | D4: No | E4: Yes | F4: No | G4: STG | H4: No data migration for STG, Parameterized scripts for simple jobs for Source to STG
A5: No. Of Tables / Files Core 25% | B5: =B3*0.25 -> 3931 | C5: No | D5: Yes | E5: Yes | F5: No | G5: Core | H5: Schema & Data migration with 10% of data loads for history during Dev
A6: No. Of Tables / Files Access 15% | B6: =B3*0.15 -> 2358.6 | C6: No | D6: Yes | E6: Yes | F6: No | G6: Access | H6: Schema & Data migration with 10% of data loads for history during Dev
A7: # of Views, Semantic Layer | B7: 25992 | C7: No | D7: No | E7: Yes | F7: Yes | G7: Access
A8: # of ETL views with business Logic | B8: 4052 | C8: No | D8: No | E8: Yes | F8: Yes | G8: Core/ Access
A9: Informatica Transformation in GBQ SP | B9: 2148 | C9: No | D9: No | E9: Yes | F9: Yes | G9: Core/ Access
A10: Stored Procedure Migration from TD to Big Query | B10: 1005 | C10: No | D10: No | E10: Yes | F10: Yes | G10: Core/ Access
A11: # TD to Sources (Oracle) Write-back Jobs | B11: 394 | C11: No | D11: No | E11: Yes | F11: Yes | G11: Access to Oracle
A12: # Cloud Storage buckets & archival Scripts | B12: 50 | C12: No | D12: No | E12: Yes | F12: Yes | G12: Archive
A13: RDM Cloud SQL Server to GBQ automated data refresh | B13: 663 | C13: No | D13: No | E13: Yes | F13: Yes | G13: Core/ Access
A14: RDM UI Build | B14: 1 | C14: No | D14: No | E14: Yes | F14: Yes | G14: UI build
A15: Scheduling & Orchestration Scripts | B15: 6039 | C15: No | D15: No | E15: No | F15: No | G15: Re-Write in Google Composer
A16: API Integration Framework-Salesforce-Cast Iron | B16: 230 | C16: No | D16: No | E16: No | F16: Yes | G16: Access to Cast Iron

Sheet Pivot (2)
A3: Sum of Total Efforts | C3: Shore
A4: Team | B4: Role | C4: India | D4: US | E4: (blank) | F4: Grand Total
A5: Architecture | B5: Data Architect | D5: 20 | F5: 20
B6: Platform/Cloud Architect | C6: 20 | D6: 3.75 | F6: 23.75
B7: Solution Architect | C7: 21 | F7: 21
A8: Data Distillation 1 | B8: Data Distillation Lead | C8: 19 | F8: 19
B9: Developer (GCP) | C9: 54 | F9: 54
B10: Developer (GCP)/ Tester | C10: 102 | F10: 102
A11: Data Distillation 2 | B11: Data Distillation Lead | C11: 35 | F11: 35
B12: Developer (GCP) | C12: 51 | F12: 51
B13: Developer (GCP)/ Tester | C13: 99.5 | F13: 99.5
A14: Data Distillation 3 | B14: Developer (GCP) | C14: 48 | F14: 48
B15: Developer (GCP)/ Tester | C15: 93 | F15: 93
A16: Data Ingestion 1 | B16: Data Ingestion Lead | C16: 19.5 | F16: 19.5
B17: Developer (GCP) | C17: 16.5 | F17: 16.5
B18: Developer (GCP)/ Tester | C18: 77.5 | F18: 77.5
A19: Data Ingestion 2 | B19: Data Ingestion Lead | C19: 18 | F19: 18
B20: Developer (GCP) | C20: 15 | F20: 15
B21: Developer (GCP)/ Tester | C21: 71 | F21: 71
A22: Data Migration 1 | B22: Data Migration Lead | C22: 19.5 | F22: 19.5
B23: Developer (GCP) | D23: 19.5 | F23: 19.5
B24: Developer (GCP)/ Tester | C24: 53.5 | F24: 53.5
A25: Data Migration 1 | B25: Developer (GCP) | C25: 35.5 | F25: 35.5
A26: Data Migration 2 | B26: Data Migration Lead | C26: 18.5 | F26: 18.5
B27: Developer (GCP) | D27: 18.5 | F27: 18.5
B28: Developer (GCP) | C28: 34.5 | F28: 34.5
B29: Developer (GCP)/ Tester | C29: 50.5 | F29: 50.5
A30: Governance | B30: Engagement Lead | D30: 20.5 | F30: 20.5
B31: Offshore Delivery Lead | C31: 20.5 | F31: 20.5
B32: Offshore Reporting Lead | C32: 20 | F32: 20
A33: Platform & DevOps | B33: DevOps SME | C33: 18.5 | F33: 18.5
B34: IDEA SME | C34: 31 | F34: 31
A35: Quality Assurance | B35: Jr Tesers | C35: 55 | F35: 55
B36: QA Lead | D36: 19 | F36: 19
B37: Sr Testers | C37: 19 | F37: 19
B38: Test Lead | C38: 19 | F38: 19
B39: Tester | C39: 19 | F39: 19
A40: Report Repoint (Q/T) | B40: Report Developer | C40: 17 | F40: 17
A41: Report Repoint (SAP) | B41: Report Developer | C41: 38 | F41: 38
B42: Report Developer / Tester | C42: 51 | F42: 51
A43: Report Repoint (Tibco) | B43: Report Developer | C43: 38 | F43: 38
B44: Report Developer / Tester | C44: 69 | F44: 69
A45: Requrements | B45: Data Analyst 1 | D45: 20 | F45: 20
B46: Data Analyst 2 | C46: 19 | F46: 19
B47: Data Analyst 3 | C47: 20 | F47: 20
B48: Lead Analyst | D48: 19 | F48: 19
A49: Reverse Engineering | B49: ETL SME (Inf + TD) | D49: 16.5 | F49: 16.5
B50: Informatica SME | C50: 35 | F50: 35
B51: Teradata SME | C51: 19 | F51: 19
A52: Schema Migration | B52: Developer (GCP) | C52: 35.5 | F52: 35.5
B53: Schema Migration Lead | C53: 18.5 | F53: 18.5
A54: UI Development | B54: UI Developer | C54: 2.5 | F54: 2.5
B55: UI/UX Designer | C55: 2.5 | F55: 2.5
A56: (blank) | B56: (blank) | E56: 0 | F56: 0
A57: Grand Total | C57: 1539 | D57: 156.75 | E57: 0 | F57: 1695.75

Sheet Sheet1
A3: Row Labels | B3: Sum of Total Efforts
A4: Architecture | B4: 1359.75 | C4: 1359.75 | D4: =C4/35610.75 -> 0.038183695 | E4: 0.08
A5: Data Distillation 1 | B5: 3675 | C5: 3675 | D5: =C5/35610.75 -> 0.10319917 | E5: 0.3
A6: Data Distillation 2 | B6: 3895.5 | C6: 3895.5 | D6: =C6/35610.75 -> 0.10939112
A7: Data Distillation 3 | B7: 2961 | C7: 2961 | D7: =C7/35610.75 -> 0.083149049
A8: Data Ingestion 1 | B8: 2383.5 | C8: 2383.5 | D8: =C8/35610.75 -> 0.066932036 | E8: 0.13
A9: Data Ingestion 2 | B9: 2184 | C9: 2184 | D9: =C9/35610.75 -> 0.061329795
A10: Data Migration 1 | B10: 2688 | C10: 2688 | D10: =C10/35610.75 -> 0.075482825 | E10: 0.26
A11: Data Migration 2 | B11: 2562 | C11: 2562 | D11: =C11/35610.75 -> 0.071944567
A12: Governance | B12: 1281 | C12: 1281 | D12: =C12/35610.75 -> 0.035972284
A13: Platform & DevOps | B13: 1039.5 | C13: 1039.5 | D13: =C13/35610.75 -> 0.029190624 | E13: 0.03
A14: Quality Assurance | B14: 2751 | C14: 2751 | D14: =C14/35610.75 -> 0.077251953 | E14: 0.09
A15: Report Repoint (Q/T) | B15: 357 | C15: 357 | D15: =C15/35610.75 -> 0.010025063 | E15: 0.13
A16: Report Repoint (SAP) | B16: 1869 | C16: 1869 | D16: =C16/35610.75 -> 0.052484152
A17: Report Repoint (Tibco) | B17: 2247 | C17: 2247 | D17: =C17/35610.75 -> 0.063098924
A18: Requrements | B18: 1638 | C18: 1638 | D18: =C18/35610.75 -> 0.045997346
A19: Reverse Engineering | B19: 1480.5 | C19: 1480.5 | D19: =C19/35610.75 -> 0.041574525
A20: Schema Migration | B20: 1134 | C20: 1134 | D20: =C20/35610.75 -> 0.031844317
A21: UI Development | B21: 105 | C21: 105 | D21: =C21/35610.75 -> 0.0029485478
A22: Grand Total | B22: 35610.75

Sheet Bayer current Rates
N1: Cost | Q1: COR
M2: ADRC rate | N2: 120 | O2: 9 hrs | Q2: 120
C3: Q-Level | D3: DE | E3: US | F3: Nearshore DE | G3: Nearshore US | H3: Offshore | I3: China | J3: Brazil | N3: =N2/9 -> 13.333333 | Q3: =Q2/8*9 -> 135
B4: =E4*$D$9 -> 701.29241 | C4: Q1 | D4: 544 | E4: 637 | F4: 242 | G4: 334 | H4: 99 | I4: 252 | J4: 196 | K4: =H4*$D$9 -> 108.99207 | N4: =N3*8 -> 106.66667 | O4: 8 hrs
B5: =E5*$D$9 -> 776.15565 | C5: Q2 | D5: 632 | E5: 705 | F5: 268 | G5: 461 | H5: 123 | I5: 415 | J5: 328 | K5: =H5*$D$9 -> 135.41439
B6: =E6*$D$9 -> 877.44121 | C6: Q3 | D6: 771 | E6: 797 | F6: 343 | G6: 512 | H6: 157 | I6: 515 | J6: 599 | K6: =H6*$D$9 -> 172.84601
B7: =E7*$D$9 -> 985.33235 | C7: Q4 | D7: 903 | E7: 895 | F7: 472 | G7: 769 | H7: 213 | I7: 709 | J7: 819 | K7: =H7*$D$9 -> 234.49809
B8: =E8*$D$9 -> 1204.4174 | C8: Q5 | D8: 1105 | E8: 1094 | F8: 657 | G8: 922 | H8: 264 | I8: 1082 | J8: 979 | K8: =H8*$D$9 -> 290.64552
C9: USD | D9: 1.10093
C10: Current Rates | M10: Daily Hours | N10: 8
C11: Q-Level | E11: US | H11: Offshore | M11: Q-Level | N11: DE | O11: US | P11: Nearshore DE | Q11: Nearshore US | R11: Offshore | S11: China | T11: Brazil
C12: Q1 | E12: =ROUNDUP(E4*$D$9,2) -> 701.3 | H12: =ROUNDUP(H4*$D$9,2) -> 109 | M12: Q1 | N12: =D12/$N$10 -> 0 | O12: =E12/$N$10 -> 87.6625 | P12: =F12/$N$10 -> 0 | Q12: =G12/$N$10 -> 0 | R12: =H12/$N$10 -> 13.625 | S12: =I12/$N$10 -> 0 | T12: =J12/$N$10 -> 0
C13: Q2 | E13: =ROUNDUP(E5*$D$9,2) -> 776.16 | H13: =ROUNDUP(H5*$D$9,2) -> 135.42 | M13: Q2 | N13: =D13/$N$10 -> 0 | O13: =E13/$N$10 -> 97.02 | P13: =F13/$N$10 -> 0 | Q13: =G13/$N$10 -> 0 | R13: =H13/$N$10 -> 16.9275 | S13: =I13/$N$10 -> 0 | T13: =J13/$N$10 -> 0
C14: Q3 | E14: =ROUNDUP(E6*$D$9,2) -> 877.45 | H14: =ROUNDUP(H6*$D$9,2) -> 172.85 | M14: Q3 | N14: =D14/$N$10 -> 0 | O14: =E14/$N$10 -> 109.68125 | P14: =F14/$N$10 -> 0 | Q14: =G14/$N$10 -> 0 | R14: =H14/$N$10 -> 21.60625 | S14: =I14/$N$10 -> 0 | T14: =J14/$N$10 -> 0
C15: Q4 | E15: =ROUNDUP(E7*$D$9,2) -> 985.34 | H15: =ROUNDUP(H7*$D$9,2) -> 234.5 | M15: Q4 | N15: =D15/$N$10 -> 0 | O15: =E15/$N$10 -> 123.1675 | P15: =F15/$N$10 -> 0 | Q15: =G15/$N$10 -> 0 | R15: =H15/$N$10 -> 29.3125 | S15: =I15/$N$10 -> 0 | T15: =J15/$N$10 -> 0
C16: Q5 | E16: =ROUNDUP(E8*$D$9,2) -> 1204.42 | H16: =ROUNDUP(H8*$D$9,2) -> 290.65 | M16: Q5 | N16: =D16/$N$10 -> 0 | O16: =E16/$N$10 -> 150.5525 | P16: =F16/$N$10 -> 0 | Q16: =G16/$N$10 -> 0 | R16: =H16/$N$10 -> 36.33125 | S16: =I16/$N$10 -> 0 | T16: =J16/$N$10 -> 0
C18: P2W Rates | E18: Onshore | F18: % Delta | H18: Offshore | I18: % Delta
C19: Q1 | E19: 648 | F19: =E19/E12-1 -> -0.076001711 | H19: 189 | I19: =H19/H12-1 -> 0.73394495
C20: Q2 | E20: 752 | F20: =E20/E13-1 -> -0.031127603 | H20: 225 | I20: =H20/H13-1 -> 0.66149756
C21: Q3 | E21: 920 | F21: =E21/E14-1 -> 0.048492792 | H21: 261 | I21: =H21/H14-1 -> 0.50997975
C22: Q4 | E22: 888 | F22: =E22/E15-1 -> -0.098788236 | H22: 279 | I22: =H22/H15-1 -> 0.18976546
C23: Q5 | E23: 1040 | F23: =E23/E16-1 -> -0.13651384 | H23: 315 | I23: =H23/H16-1 -> 0.08377774

Sheet Old_PP & RL Plan
B23: May with small team
AH26: 21
C27: 29043
G30: 1 | H30: 2 | I30: 3 | J30: 4 | K30: 5 | L30: 6 | M30: 7 | N30: 8 | O30: 9 | P30: 10 | Q30: 11 | R30: 12 | S30: 13 | T30: 14 | U30: 15 | V30: 16 | W30: 17 | X30: 18 | Y30: 19 | Z30: 20 | AA30: 21 | AB30: 22 | AK30: 0.2
AK31: 0.25
G32: 44682 | H32: 44713 | I32: 44743 | J32: 44774 | K32: 44805 | L32: 44835 | M32: 44866 | N32: 44896 | O32: 44927 | P32: 44958 | Q32: 44986 | R32: 45017 | S32: 45047 | T32: 45078 | U32: 45108 | V32: 45139 | W32: 45170 | X32: 45200 | Y32: 45231 | Z32: 45261 | AA32: 45292 | AB32: 45323
A33: BU | B33: SL | C33: Role | D33: Grade | E33: Shore | G33: 1 | H33: 2 | I33: 3 | J33: 4 | K33: 5 | L33: 6 | M33: 7 | N33: 8 | O33: 9 | P33: 10 | Q33: 11 | R33: 12 | S33: 13 | T33: 14 | U33: 15 | V33: 16 | W33: 17 | X33: 18 | Y33: 19 | Z33: 20 | AA33: 21 | AB33: 22 | AD33: Total PDs | AE33: Q Level | AF33: Current Daily Rate $ | AG33: Total Price | AH33: P2W Rates | AI33: Total Price as per P2W | AJ33: ADRC Inc TRIO | AL33: USD ADRC Ex TRIO | AM33: Total Cost | AR33: GCP | AS33: Efforts | AT33: Loading | AU33: Delta
A34: I&D | B34: GCP | C34: Engagment Manager | D34: E1 | E34: On | G34: 1 | H34: 1 | I34: 1 | J34: 1 | K34: 1 | L34: 1 | M34: 1 | N34: 1 | O34: 1 | P34: 1 | Q34: 1 | R34: 1 | S34: 1 | T34: 1 | U34: 1 | V34: 1 | W34: 1 | X34: 1 | Y34: 1 | Z34: 1 | AA34: 1 | AB34: 1 | AD34: =21*SUM(G34:AB34) -> 462 | AE34: =VLOOKUP(D34,$H$65:$J$72,3,0) -> Q5 | AF34: =VLOOKUP(AE34,'Bayer current Rates'!$C$12:$E$16,3,0) -> 1204.42 | AG34: =AF34*AD34 -> 556442.04 | AH34: =VLOOKUP(AE34,'Bayer current Rates'!$C$19:$H$23,3,0) -> 1040 | AI34: =AD34*AH34 -> 480480 | AJ34: 1520 | AK34: =AJ34*(1-$AK$30) -> 1216 | AL34: =AK34 -> 1216 | AM34: =AL34*AD34 -> 561792 | AS34: =SUM('Estimator -3'!N16:N25,'Estimator -3'!N33)*1.36 -> 24837.86 | AT34: =SUM(AD34:AD38,AD40:AD50) -> 24801 | AU34: =AS34-AT34 -> 36.859822
A35: I&D | B35: GCP | C35: GPC Data Architect | D35: D2 | E35: On | G35: 1 | H35: 1 | I35: 1 | J35: 1 | K35: 1 | L35: 1 | M35: 1 | N35: 1 | O35: 1 | P35: 1 | Q35: 1 | R35: 1 | S35: 1 | T35: 1 | U35: 1 | V35: 1 | W35: 1 | X35: 1 | Y35: 1 | Z35: 1 | AA35: 1 | AB35: 1 | AD35: =21*SUM(G35:AB35) -> 462 | AE35: =VLOOKUP(D35,$H$65:$J$72,3,0) -> Q5 | AF35: =VLOOKUP(AE35,'Bayer current Rates'!$C$12:$E$16,3,0) -> 1204.42 | AG35: =AF35*AD35 -> 556442.04 | AH35: =VLOOKUP(AE35,'Bayer current Rates'!$C$19:$H$23,3,0) -> 1040 | AI35: =AD35*AH35 -> 480480 | AJ35: 1407.8053 | AK35: =AJ35*(1-$AK$30) -> 1126.2443 | AL35: =AK35 -> 1126.2443 | AM35: =AL35*AD35 -> 520324.85
A36: I&D | B36: GCP | C36: BigQuery Data Analysts (With Tera Backgroud) | D36: C1 | E36: On | G36: 2 | H36: 2 | I36: 3 | J36: 3 | K36: 3 | L36: 3 | M36: 3 | N36: 3 | O36: 3 | P36: 3 | Q36: 3 | R36: 3 | S36: 3 | T36: 3 | U36: 3 | V36: 3 | W36: 3 | X36: 3 | Y36: 3 | Z36: 3 | AA36: 2 | AB36: 1 | AD36: =21*SUM(G36:AB36) -> 1281 | AE36: =VLOOKUP(D36,$H$65:$J$72,3,0) -> Q2 | AF36: =VLOOKUP(AE36,'Bayer current Rates'!$C$12:$E$16,3,0) -> 776.16 | AG36: =AF36*AD36 -> 994260.96 | AH36: =VLOOKUP(AE36,'Bayer current Rates'!$C$19:$H$23,3,0) -> 752 | AI36: =AD36*AH36 -> 963312 | AJ36: 1017.3831 | AK36: =AJ36*(1-$AK$30) -> 813.9065 | AL36: =AK36 -> 813.9065 | AM36: =AL36*AD36 -> 1042614.2
A37: I&D | B37: GCP | C37: GCP Platform Architect | D37: C2 | E37: On | G37: 1 | H37: 1 | I37: 1 | J37: 1 | K37: 1 | L37: 1 | M37: 1 | N37: 1 | O37: 1 | P37: 1 | Q37: 1 | R37: 1 | S37: 1 | T37: 1 | U37: 1 | V37: 1 | W37: 1 | X37: 1 | Y37: 1 | Z37: 1 | AA37: 1 | AB37: 1 | AD37: =21*SUM(G37:AB37) -> 462 | AE37: =VLOOKUP(D37,$H$65:$J$72,3,0) -> Q3 | AF37: =VLOOKUP(AE37,'Bayer current Rates'!$C$12:$E$16,3,0) -> 877.45 | AG37: =AF37*AD37 -> 405381.9 | AH37: =VLOOKUP(AE37,'Bayer current Rates'!$C$19:$H$23,3,0) -> 920 | AI37: =AD37*AH37 -> 425040 | AJ37: 1017.3831 | AK37: =AJ37*(1-$AK$30) -> 813.9065 | AL37: =AK37 -> 813.9065 | AM37: =AL37*AD37 -> 376024.8
A38: I&D | B38: GCP | C38: SQL SMEs (with Teradata background) | D38: C2 | E38: On | G38: 1 | H38: 1 | I38: 2 | J38: 2 | K38: 2 | L38: 2 | M38: 2 | N38: 2 | O38: 2 | P38: 2 | Q38: 2 | R38: 2 | S38: 2 | T38: 2 | U38: 2 | V38: 2 | W38: 2 | X38: 2 | Y38: 2 | Z38: 2 | AA38: 2 | AB38: 1 | AD38: =21*SUM(G38:AB38) -> 861 | AE38: =VLOOKUP(D38,$H$65:$J$72,3,0) -> Q3 | AF38: =VLOOKUP(AE38,'Bayer current Rates'!$C$12:$E$16,3,0) -> 877.45 | AG38: =AF38*AD38 -> 755484.45 | AH38: =VLOOKUP(AE38,'Bayer current Rates'!$C$19:$H$23,3,0) -> 920 | AI38: =AD38*AH38 -> 792120 | AJ38: 1017.3831 | AK38: =AJ38*(1-$AK$30) -> 813.9065 | AL38: =AK38 -> 813.9065 | AM38: =AL38*AD38 -> 700773.49
A39: Testing BU | B39: Tera | C39: Testing Lead | D39: C2 | E39: On | G39: 1 | H39: 1 | I39: 1 | J39: 1 | K39: 1 | L39: 1 | M39: 1 | N39: 1 | O39: 1 | P39: 1 | Q39: 1 | R39: 1 | S39: 1 | T39: 1 | U39: 1 | V39: 1 | W39: 1 | X39: 1 | Y39: 1 | Z39: 1 | AA39: 1 | AB39: 1 | AD39: =21*SUM(G39:AB39) -> 462 | AE39: =VLOOKUP(D39,$H$65:$J$72,3,0) -> Q3 | AF39: =VLOOKUP(AE39,'Bayer current Rates'!$C$12:$E$16,3,0) -> 877.45 | AG39: =AF39*AD39 -> 405381.9 | AH39: =VLOOKUP(AE39,'Bayer current Rates'!$C$19:$H$23,3,0) -> 920 | AI39: =AD39*AH39 -> 425040 | AJ39: 800.51502 | AK39: =AJ39 -> 800.51502 | AL39: =AK39 -> 800.51502 | AM39: =AL39*AD39 -> 369837.94
A40: I&D | B40: GCP | C40: Program Manager/Delivery Lead | D40: D2 | E40: Off | G40: 1 | H40: 1 | I40: 1 | J40: 1 | K40: 1 | L40: 1 | M40: 1 | N40: 1 | O40: 1 | P40: 1 | Q40: 1 | R40: 1 | S40: 1 | T40: 1 | U40: 1 | V40: 1 | W40: 1 | X40: 1 | Y40: 1 | Z40: 1 | AA40: 1 | AB40: 1 | AD40: =21*SUM(G40:AB40) -> 462 | AE40: =VLOOKUP(D40,$H$65:$J$72,3,0) -> Q5 | AF40: =VLOOKUP(AE40,'Bayer current Rates'!$C$12:$H$16,6,0) -> 290.65 | AG40: =AF40*AD40 -> 134280.3 | AH40: =VLOOKUP(AE40,'Bayer current Rates'!$C$19:$H$23,6,0) -> 315 | AI40: =AD40*AH40 -> 145530 | AJ40: 227.46 | AK40: =AJ40*(1-$AK$31) -> 170.595 | AL40: =AK40*'Bayer current Rates'!$D$9 -> 187.81315 | AM40: =AL40*AD40 -> 86769.677
A41: I&D | B41: GCP | C41: Lead GCP Data Architect | D41: D1 | E41: Off | G41: 1 | H41: 1 | I41: 1 | J41: 1 | K41: 1 | L41: 1 | M41: 1 | N41: 1 | O41: 1 | P41: 1 | Q41: 1 | R41: 1 | S41: 1 | T41: 1 | U41: 1 | V41: 1 | W41: 1 | X41: 1 | Y41: 1 | Z41: 1 | AA41: 1 | AB41: 1 | AD41: =21*SUM(G41:AB41) -> 462 | AE41: =VLOOKUP(D41,$H$65:$J$72,3,0) -> Q4 | AF41: =VLOOKUP(AE41,'Bayer current Rates'!$C$12:$H$16,6,0) -> 234.5 | AG41: =AF41*AD41 -> 108339 | AH41: =VLOOKUP(AE41,'Bayer current Rates'!$C$19:$H$23,6,0) -> 279 | AI41: =AD41*AH41 -> 128898 | AJ41: 198.12 | AK41: =AJ41*(1-$AK$31) -> 148.59 | AL41: =AK41*'Bayer current Rates'!$D$9 -> 163.58719 | AM41: =AL41*AD41 -> 75577.281 | AV41: 1522574.3 | AW41: 118812.24 | AX41: 3503735.9 | AY41: 379153.99 | AZ41: =SUM(AV41:AY41) -> 5524276.4
A42: I&D | B42: GCP | C42: GCP Data Engineer Lead(s) | D42: C2 | E42: Off | I42: 3 | J42: 3 | K42: 3 | L42: 3 | M42: 3 | N42: 3 | O42: 3 | P42: 3 | Q42: 3 | R42: 3 | S42: 3 | T42: 3 | U42: 3 | V42: 3 | W42: 3 | X42: 3 | Y42: 3 | Z42: 3 | AA42: 3 | AB42: 2 | AD42: =21*SUM(G42:AB42) -> 1239 | AE42: =VLOOKUP(D42,$H$65:$J$72,3,0) -> Q3 | AF42: =VLOOKUP(AE42,'Bayer current Rates'!$C$12:$H$16,6,0) -> 172.85 | AG42: =AF42*AD42 -> 214161.15 | AH42: =VLOOKUP(AE42,'Bayer current Rates'!$C$19:$H$23,6,0) -> 261 | AI42: =AD42*AH42 -> 323379 | AJ42: 161.85 | AK42: =AJ42*(1-$AK$31) -> 121.3875 | AL42: =AK42*'Bayer current Rates'!$D$9 -> 133.63914 | AM42: =AL42*AD42 -> 165578.89 | AV42: =SUM(AV41:AW41) -> 1641386.6 | AX42: =SUM(AX41:AY41) -> 3882889.9
A43: I&D | B43: GCP | C43: GCP Sr Data Engineer(s) | D43: C1 | E43: Off | I43: 4 | J43: 4 | K43: 4 | L43: 4 | M43: 4 | N43: 4 | O43: 4 | P43: 4 | Q43: 4 | R43: 4 | S43: 4 | T43: 4 | U43: 4 | V43: 4 | W43: 4 | X43: 4 | Y43: 4 | Z43: 3 | AA43: 3 | AB43: 2 | AD43: =21*SUM(G43:AB43) -> 1596 | AE43: =VLOOKUP(D43,$H$65:$J$72,3,0) -> Q2 | AF43: =VLOOKUP(AE43,'Bayer current Rates'!$C$12:$H$16,6,0) -> 135.42 | AG43: =AF43*AD43 -> 216130.32 | AH43: =VLOOKUP(AE43,'Bayer current Rates'!$C$19:$H$23,6,0) -> 225 | AI43: =AD43*AH43 -> 359100 | AJ43: 118.66 | AK43: =AJ43*(1-$AK$31) -> 88.995 | AL43: =AK43*'Bayer current Rates'!$D$9 -> 97.977265 | AM43: =AL43*AD43 -> 156371.72 | AZ43: =AV42+AW45 -> 1741386.6
A44: I&D | B44: GCP | C44: GCP Data Engineer (s) | D44: B2 | E44: Off | I44: 5 | J44: 5 | K44: 8 | L44: 8 | M44: 8 | N44: 8 | O44: 8 | P44: 8 | Q44: 8 | R44: 8 | S44: 8 | T44: 8 | U44: 8 | V44: 8 | W44: 8 | X44: 8 | Y44: 8 | Z44: 8 | AA44: 8 | AB44: 5 | AD44: =21*SUM(G44:AB44) -> 3171 | AE44: =VLOOKUP(D44,$H$65:$J$72,3,0) -> Q2 | AF44: =VLOOKUP(AE44,'Bayer current Rates'!$C$12:$H$16,6,0) -> 135.42 | AG44: =AF44*AD44 -> 429416.82 | AH44: =VLOOKUP(AE44,'Bayer current Rates'!$C$19:$H$23,6,0) -> 225 | AI44: =AD44*AH44 -> 713475 | AJ44: 80.52 | AK44: =AJ44*(1-$AK$31) -> 60.39 | AL44: =AK44*'Bayer current Rates'!$D$9 -> 66.485163 | AM44: =AL44*AD44 -> 210824.45 | AV44: Onshore | AW44: Offshore | AZ44: =AX42+AV45 -> 4282889.9
A45: I&D | B45: GCP | C45: GCP Data Engineer(s) | D45: B1 | E45: Off | I45: 5 | J45: 10 | K45: 10 | L45: 10 | M45: 10 | N45: 10 | O45: 10 | P45: 10 | Q45: 10 | R45: 10 | S45: 10 | T45: 10 | U45: 10 | V45: 10 | W45: 10 | X45: 10 | Y45: 10 | Z45: 10 | AA45: 10 | AB45: 5 | AD45: =21*SUM(G45:AB45) -> 3990 | AE45: =VLOOKUP(D45,$H$65:$J$72,3,0) -> Q1 | AF45: =VLOOKUP(AE45,'Bayer current Rates'!$C$12:$H$16,6,0) -> 109 | AG45: =AF45*AD45 -> 434910 | AH45: =VLOOKUP(AE45,'Bayer current Rates'!$C$19:$H$23,6,0) -> 189 | AI45: =AD45*AH45 -> 754110 | AJ45: 62.56 | AK45: =AJ45*(1-$AK$31) -> 46.92 | AL45: =AK45*'Bayer current Rates'!$D$9 -> 51.655636 | AM45: =AL45*AD45 -> 206105.99 | AV45: 400000 | AW45: 100000 | AX45: =SUM(AV45:AW45) -> 500000 | AZ45: =AZ43+AZ44 -> 6024276.4
A46: I&D | B46: GCP | C46: GCP Data Engineer/Testerer(s) | D46: B1 | E46: Off | I46: 8 | J46: 8 | K46: 8 | L46: 8 | M46: 9 | N46: 9 | O46: 9 | P46: 9 | Q46: 9 | R46: 9 | S46: 9 | T46: 9 | U46: 9 | V46: 9 | W46: 9 | X46: 9 | Y46: 9 | Z46: 9 | AA46: 9 | AB46: 5 | AD46: =21*SUM(G46:AB46) -> 3612 | AE46: =VLOOKUP(D46,$H$65:$J$72,3,0) -> Q1 | AF46: =VLOOKUP(AE46,'Bayer current Rates'!$C$12:$H$16,6,0) -> 109 | AG46: =AF46*AD46 -> 393708 | AH46: =VLOOKUP(AE46,'Bayer current Rates'!$C$19:$H$23,6,0) -> 189 | AI46: =AD46*AH46 -> 682668 | AJ46: 62.56 | AK46: =AJ46*(1-$AK$31) -> 46.92 | AL46: =AK46*'Bayer current Rates'!$D$9 -> 51.655636 | AM46: =AL46*AD46 -> 186580.16 | AV46: Travel | AW46: Misc | AZ46: =AZ45/(1-40%) -> 10040461
A47: I&D | B47: GCP | C47: GCP Data Engineer/Testerer (s) | D47: A5 | E47: Off | I47: 8 | J47: 8 | K47: 10 | L47: 13 | M47: 15 | N47: 15 | O47: 15 | P47: 15 | Q47: 15 | R47: 15 | S47: 15 | T47: 15 | U47: 15 | V47: 15 | W47: 15 | X47: 15 | Y47: 15 | Z47: 10 | AA47: 10 | AB47: 7 | AD47: =21*SUM(G47:AB47) -> 5481 | AE47: =VLOOKUP(D47,$H$65:$J$72,3,0) -> Q1 | AF47: =VLOOKUP(AE47,'Bayer current Rates'!$C$12:$H$16,6,0) -> 109 | AG47: =AF47*AD47 -> 597429 | AH47: =VLOOKUP(AE47,'Bayer current Rates'!$C$19:$H$23,6,0) -> 189 | AI47: =AD47*AH47 -> 1035909 | AJ47: 34.04 | AK47: =AJ47*(1-$AK$31) -> 25.53 | AL47: =AK47*'Bayer current Rates'!$D$9 -> 28.106743 | AM47: =AL47*AD47 -> 154053.06 | AV47: =AV45/22 -> 18181.818 | AW47: =AW45/22 -> 4545.4545 | AZ47: =AZ46*1.08 -> 10843698
A48: I&D | B48: GCP | C48: SQL SMEs (with Teradata background) | D48: B2 | E48: Off | I48: 1 | J48: 1 | K48: 1 | L48: 1 | M48: 1 | N48: 1 | O48: 1 | P48: 1 | Q48: 1 | R48: 1 | S48: 1 | T48: 1 | U48: 1 | V48: 1 | W48: 1 | X48: 1 | Y48: 1 | Z48: 1 | AA48: 1 | AB48: 1 | AD48: =21*SUM(G48:AB48) -> 420 | AE48: =VLOOKUP(D48,$H$65:$J$72,3,0) -> Q2 | AF48: =VLOOKUP(AE48,'Bayer current Rates'!$C$12:$H$16,6,0) -> 135.42 | AG48: =AF48*AD48 -> 56876.4 | AH48: =VLOOKUP(AE48,'Bayer current Rates'!$C$19:$H$23,6,0) -> 225 | AI48: =AD48*AH48 -> 94500 | AJ48: 80.52 | AK48: =AJ48*(1-$AK$31) -> 60.39 | AL48: =AK48*'Bayer current Rates'!$D$9 -> 66.485163 | AM48: =AL48*AD48 -> 27923.768
A49: I&D | B49: GCP | C49: GCP DE (with Infomatica Background) | D49: B2 | E49: Off | I49: 1 | J49: 1 | K49: 1 | L49: 1 | M49: 1 | N49: 1 | O49: 1 | P49: 1 | Q49: 1 | R49: 1 | S49: 1 | T49: 1 | U49: 1 | V49: 1 | W49: 1 | X49: 1 | Y49: 1 | Z49: 1 | AA49: 1 | AB49: 1 | AD49: =21*SUM(G49:AB49) -> 420 | AE49: =VLOOKUP(D49,$H$65:$J$72,3,0) -> Q2 | AF49: =VLOOKUP(AE49,'Bayer current Rates'!$C$12:$H$16,6,0) -> 135.42 | AG49: =AF49*AD49 -> 56876.4 | AH49: =VLOOKUP(AE49,'Bayer current Rates'!$C$19:$H$23,6,0) -> 225 | AI49: =AD49*AH49 -> 94500 | AJ49: 80.52 | AK49: =AJ49*(1-$AK$31) -> 60.39 | AL49: =AK49*'Bayer current Rates'!$D$9 -> 66.485163 | AM49: =AL49*AD49 -> 27923.768
A50: I&D | B50: GCP | C50: GCP DE (with Infomatica Background) | D50: B1 | E50: Off | I50: 1 | J50: 1 | K50: 1 | L50: 1 | M50: 1 | N50: 1 | O50: 1 | P50: 1 | Q50: 1 | R50: 1 | S50: 1 | T50: 1 | U50: 1 | V50: 1 | W50: 1 | X50: 1 | Y50: 1 | Z50: 1 | AA50: 1 | AB50: 1 | AD50: =21*SUM(G50:AB50) -> 420 | AE50: =VLOOKUP(D50,$H$65:$J$72,3,0) -> Q1 | AF50: =VLOOKUP(AE50,'Bayer current Rates'!$C$12:$H$16,6,0) -> 109 | AG50: =AF50*AD50 -> 45780 | AH50: =VLOOKUP(AE50,'Bayer current Rates'!$C$19:$H$23,6,0) -> 189 | AI50: =AD50*AH50 -> 79380 | AJ50: 62.56 | AK50: =AJ50*(1-$AK$31) -> 46.92 | AL50: =AK50*'Bayer current Rates'!$D$9 -> 51.655636 | AM50: =AL50*AD50 -> 21695.367
A51: I&D | B51: SAP BO | C51: Sr. BO Developer | D51: C1 | E51: Off | K51: 1 | L51: 1 | M51: 1 | N51: 1 | O51: 1 | P51: 1 | Q51: 1 | R51: 1 | S51: 1 | T51: 1 | U51: 1 | V51: 1 | W51: 1 | AD51: =21*SUM(G51:AB51) -> 273 | AE51: =VLOOKUP(D51,$H$65:$J$72,3,0) -> Q2 | AF51: =VLOOKUP(AE51,'Bayer current Rates'!$C$12:$H$16,6,0) -> 135.42 | AG51: =AF51*AD51 -> 36969.66 | AH51: =VLOOKUP(AE51,'Bayer current Rates'!$C$19:$H$23,6,0) -> 225 | AI51: =AD51*AH51 -> 61425 | AJ51: 118.66 | AK51: =AJ51*(1-$AK$31) -> 88.995 | AL51: =AK51*'Bayer current Rates'!$D$9 -> 97.977265 | AM51: =AL51*AD51 -> 26747.793 | AR51: SAP BO | AS51: Efforts | AT51: Loading | AU51: Delta
A52: I&D | B52: SAP BO | C52: Jr. BO Developer | D52: B2 | E52: Off | M52: 1 | N52: 1 | O52: 1 | P52: 1 | Q52: 1 | R52: 1 | S52: 1 | T52: 1 | U52: 1 | V52: 1 | W52: 1 | X52: 1 | Y52: 1 | Z52: 1 | AA52: 1 | AB52: 1 | AD52: =21*SUM(G52:AB52) -> 336 | AE52: =VLOOKUP(D52,$H$65:$J$72,3,0) -> Q2 | AF52: =VLOOKUP(AE52,'Bayer current Rates'!$C$12:$H$16,6,0) -> 135.42 | AG52: =AF52*AD52 -> 45501.12 | AH52: =VLOOKUP(AE52,'Bayer current Rates'!$C$19:$H$23,6,0) -> 225 | AI52: =AD52*AH52 -> 75600 | AJ52: 80.52 | AK52: =AJ52*(1-$AK$31) -> 60.39 | AL52: =AK52*'Bayer current Rates'!$D$9 -> 66.485163 | AM52: =AL52*AD52 -> 22339.015 | AS52: =SUM('Estimator -3'!N27:N28)*1.36 -> 615.53147 | AT52: =SUM(AD51:AD52) -> 609 | AU52: =AS52-AT52 -> 6.5314667
A53: I&D | B53: Rep & Viz | C53: Sr SpotFire/Qlik/Tab SME | D53: C1 | E53: Off | K53: 1 | L53: 1 | M53: 1 | N53: 1 | O53: 1 | P53: 1 | Q53: 1 | R53: 1 | S53: 1 | T53: 1 | U53: 1 | V53: 1 | AD53: =21*SUM(G53:AB53) -> 252 | AE53: =VLOOKUP(D53,$H$65:$J$72,3,0) -> Q2 | AF53: =VLOOKUP(AE53,'Bayer current Rates'!$C$12:$H$16,6,0) -> 135.42 | AG53: =AF53*AD53 -> 34125.84 | AH53: =VLOOKUP(AE53,'Bayer current Rates'!$C$19:$H$23,6,0) -> 225 | AI53: =AD53*AH53 -> 56700 | AJ53: 118.66 | AK53: =AJ53*(1-$AK$31) -> 88.995 | AL53: =AK53*'Bayer current Rates'!$D$9 -> 97.977265 | AM53: =AL53*AD53 -> 24690.271 | AR53: SP/Tab/Qlik | AS53: Efforts | AT53: Loading | AU53: Delta
A54: I&D | B54: Rep & Viz | C54: Spotfire /QlikSME | D54: B2 | E54: Off | K54: 1 | L54: 1 | M54: 1 | N54: 1 | O54: 1 | P54: 1 | Q54: 1 | R54: 1 | S54: 1 | T54: 1 | U54: 1 | V54: 1 | W54: 1 | X54: 1 | Y54: 1 | Z54: 1 | AA54: 1 | AB54: 1 | AD54: =21*SUM(G54:AB54) -> 378 | AE54: =VLOOKUP(D54,$H$65:$J$72,3,0) -> Q2 | AF54: =VLOOKUP(AE54,'Bayer current Rates'!$C$12:$H$16,6,0) -> 135.42 | AG54: =AF54*AD54 -> 51188.76 | AH54: =VLOOKUP(AE54,'Bayer current Rates'!$C$19:$H$23,6,0) -> 225 | AI54: =AD54*AH54 -> 85050 | AJ54: 80.52 | AK54: =AJ54*(1-$AK$31) -> 60.39 | AL54: =AK54*'Bayer current Rates'!$D$9 -> 66.485163 | AM54: =AL54*AD54 -> 25131.392 | AS54: =SUM('Estimator -3'!N26,'Estimator -3'!N29:N32)*1.36 -> 927.45956 | AT54: =SUM(AD53:AD55) -> 924 | AU54: =AS54-AT54 -> 3.4595556
A55: I&D | B55: Rep & Viz | C55: Jr SpotFire/Tableu SME | D55: B1 | E55: Off | O55: 1 | P55: 1 | Q55: 1 | R55: 1 | S55: 1 | T55: 1 | U55: 1 | V55: 1 | W55: 1 | X55: 1 | Y55: 1 | Z55: 1 | AA55: 1 | AB55: 1 | AD55: =21*SUM(G55:AB55) -> 294 | AE55: =VLOOKUP(D55,$H$65:$J$72,3,0) -> Q1 | AF55: =VLOOKUP(AE55,'Bayer current Rates'!$C$12:$H$16,6,0) -> 109 | AG55: =AF55*AD55 -> 32046 | AH55: =VLOOKUP(AE55,'Bayer current Rates'!$C$19:$H$23,6,0) -> 189 | AI55: =AD55*AH55 -> 55566 | AJ55: 62.56 | AK55: =AJ55*(1-$AK$31) -> 46.92 | AL55: =AK55*'Bayer current Rates'!$D$9 -> 51.655636 | AM55: =AL55*AD55 -> 15186.757
A56: Testing BU | B56: Testing | C56: Test Lead | D56: C1 | E56: Off | J56: 1 | K56: 1 | L56: 1 | M56: 1 | N56: 1 | O56: 1 | P56: 1 | Q56: 1 | R56: 1 | S56: 1 | T56: 1 | U56: 1 | V56: 1 | W56: 1 | X56: 1 | Y56: 1 | Z56: 1 | AA56: 1 | AD56: =21*SUM(G56:AB56) -> 378 | AE56: =VLOOKUP(D56,$H$65:$J$72,3,0) -> Q2 | AF56: =VLOOKUP(AE56,'Bayer current Rates'!$C$12:$H$16,6,0) -> 135.42 | AG56: =AF56*AD56 -> 51188.76 | AH56: =VLOOKUP(AE56,'Bayer current Rates'!$C$19:$H$23,6,0) -> 225 | AI56: =AD56*AH56 -> 85050 | AJ56: 84 | AK56: =AJ56 -> 84 | AL56: =AK56 -> 84 | AM56: =AL56*AD56 -> 31752 | AR56: Testing | AS56: Efforts | AT56: Loading | AU56: Delta
A57: Testing BU | B57: Testing | C57: Sr Testers & Data / Report validators | D57: B2 | E57: Off | J57: 1 | K57: 1 | L57: 1 | M57: 1 | N57: 1 | O57: 1 | P57: 1 | Q57: 1 | R57: 1 | S57: 1 | T57: 1 | U57: 1 | V57: 1 | W57: 1 | X57: 1 | Y57: 1 | Z57: 1 | AA57: 1 | AD57: =21*SUM(G57:AB57) -> 378 | AE57: =VLOOKUP(D57,$H$65:$J$72,3,0) -> Q2 | AF57: =VLOOKUP(AE57,'Bayer current Rates'!$C$12:$H$16,6,0) -> 135.42 | AG57: =AF57*AD57 -> 51188.76 | AH57: =VLOOKUP(AE57,'Bayer current Rates'!$C$19:$H$23,6,0) -> 225 | AI57: =AD57*AH57 -> 85050 | AJ57: 63 | AK57: =AJ57 -> 63 | AL57: =AK57 -> 63 | AM57: =AL57*AD57 -> 23814 | AS57: ='Estimator -3'!B7 -> 2715 | AT57: =SUM(AD39,AD56:AD59) -> 2709 | AU57: =AS57-AT57 -> 6
A58: Testing BU | B58: Testing | C58: Tester & Data / Report validators | D58: B1 | E58: Off | J58: 1 | K58: 1 | L58: 1 | M58: 1 | N58: 1 | O58: 1 | P58: 1 | Q58: 1 | R58: 1 | S58: 1 | T58: 1 | U58: 1 | V58: 1 | W58: 1 | X58: 1 | Y58: 1 | Z58: 1 | AA58: 1 | AD58: =21*SUM(G58:AB58) -> 378 | AE58: =VLOOKUP(D58,$H$65:$J$72,3,0) -> Q1 | AF58: =VLOOKUP(AE58,'Bayer current Rates'!$C$12:$H$16,6,0) -> 109 | AG58: =AF58*AD58 -> 41202 | AH58: =VLOOKUP(AE58,'Bayer current Rates'!$C$19:$H$23,6,0) -> 189 | AI58: =AD58*AH58 -> 71442 | AJ58: 46 | AK58: =AJ58 -> 46 | AL58: =AK58 -> 46 | AM58: =AL58*AD58 -> 17388
A59: Testing BU | B59: Testing | C59: Jr Tesers & Data / Report validators | D59: A5 | E59: Off | K59: 1 | L59: 4 | M59: 4 | N59: 4 | O59: 4 | P59: 4 | Q59: 4 | R59: 3 | S59: 3 | T59: 3 | U59: 3 | V59: 3 | W59: 3 | X59: 3 | Y59: 3 | Z59: 3 | AA59: 1 | AD59: =21*SUM(G59:AB59) -> 1113 | AE59: =VLOOKUP(D59,$H$65:$J$72,3,0) -> Q1 | AF59: =VLOOKUP(AE59,'Bayer current Rates'!$C$12:$H$16,6,0) -> 109 | AG59: =AF59*AD59 -> 121317 | AH59: =VLOOKUP(AE59,'Bayer current Rates'!$C$19:$H$23,6,0) -> 189 | AI59: =AD59*AH59 -> 210357 | AJ59: 35 | AK59: =AJ59 -> 35 | AL59: =AK59 -> 35 | AM59: =AL59*AD59 -> 38955
G60: =SUM(G34:G59)*21 -> 189 | H60: =SUM(H34:H59)*21 -> 189 | I60: =SUM(I34:I59)*21 -> 987 | J60: =SUM(J34:J59)*21 -> 1155 | K60: =SUM(K34:K59)*21 -> 1344 | L60: =SUM(L34:L59)*21 -> 1470 | M60: =SUM(M34:M59)*21 -> 1554 | N60: =SUM(N34:N59)*21 -> 1554 | ... AB60: =SUM(AB34:AB59)*21 -> 840 | AD60: =SUM(AD34:AD59) -> 29043 | AE60: =C27-AD60 -> 0 | AG60: =SUM(AG34:AG59) -> 6826028.6 | AI60: =SUM(AI34:AI59) -> 8764161 | AM60: =SUM(AM34:AM59) -> 5116775.7
C61: 10872146 | G61: =G60/$AD$60 -> 0.0065075922 | H61: =H60/$AD$60 -> 0.0065075922 | I61: =I60/$AD$60 -> 0.033984093 | J61: =J60/$AD$60 -> 0.039768619 | K61: =K60/$AD$60 -> 0.046276211 | L61: =L60/$AD$60 -> 0.050614606 | M61: =M60/$AD$60 -> 0.053506869 | N61: =N60/$AD$60 -> 0.053506869 | ... AB61: =AB60/$AD$60 -> 0.028922632 | AD61: =AD60*1.08 -> 31366.44 | AG61: 5431917.3 | AI61: =AG61 -> 5431917.3
G62: =$C$61*G61 -> 70751.494 | H62: =$C$61*H61 -> 70751.494 | I62: =$C$61*I61 -> 369480.03 | J62: =$C$61*J61 -> 432370.24 | K62: =$C$61*K61 -> 503121.74 | L62: =$C$61*L61 -> 550289.4 | M62: =$C$61*M61 -> 581734.51 | N62: =$C$61*N61 -> 581734.51 | ... AC62: =$C$61*AC61 -> 0 | AG62: =1-AG61/AG60 -> 0.20423461 | AI62: =1-AI61/AI60 -> 0.38021251
G63: 0.0065075922 | H63: 0.0065075922 | I63: 0.033984093 | J63: 0.039768619 | K63: 0.046276211 | L63: 0.050614606 | M63: 0.053506869 | N63: 0.053506869 | O63: 0.054229935 | P63: 0.054229935 | Q63: 0.054229935 | R63: 0.053506869 | S63: 0.053506869 | T63: 0.053506869 | U63: 0.053506869 | V63: 0.053506869 | W63: 0.052783803 | X63: 0.052060738 | Y63: 0.052060738 | Z63: 0.047722343 | AA63: 0.045553145 | AB63: 0.028922632 | AD63: =SUM(AD56:AD59) -> 2247 | AE63: =AD39 -> 462
H64: Grades | I64: % Allocation
G65: Q5 | H65: E1 | I65: =SUMIF($D$34:$D$59,H65,$AD$34:$AD$59)/SUM($AD$34:$AD$59) -> 0.015907448 | J65: Q5 | R65: =29043*9*27 -> 7057449 | AD65: ON | AF65: Off
G66: Q5 | H66: D2 | I66: =SUMIF($D$34:$D$59,H66,$AD$34:$AD$59)/SUM($AD$34:$AD$59) -> 0.031814895 | J66: Q5 | Q66: Contingency | R66: =R65*1.08 -> 7622044.9 | AC66: =AE66/$AE$71 -> 0 | AD66: Q1 | AE66: =SUMIF($AE$34:$AE$39,$AD66,$AD$34:$AD$39) -> 0 | AF66: Q1 | AG66: =SUMIF($AE$40:$AE$59,$AF66,$AD$40:$AD$59) -> 15288 | AH66: =AG66/$AG$71 -> 0.61022632
G67: Q4 | H67: D1 | I67: =SUMIF($D$34:$D$59,H67,$AD$34:$AD$59)/SUM($AD$34:$AD$59) -> 0.015907448 | J67: Q4 | X67: 480 | AC67: =AE67/$AE$71 -> 0.32105263 | AD67: Q2 | AE67: =SUMIF($AE$34:$AE$39,$AD67,$AD$34:$AD$39) -> 1281 | AF67: Q2 | AG67: =SUMIF($AE$40:$AE$59,$AF67,$AD$40:$AD$59) -> 7602 | AH67: =AG67/$AG$71 -> 0.30343671
G68: Q3 | H68: C2 | I68: =SUMIF($D$34:$D$59,H68,$AD$34:$AD$59)/SUM($AD$34:$AD$59) -> 0.10412148 | J68: Q3 | X68: =X67*AD60 -> 13940640 | Y68: =X68*1.08 -> 15055891 | AC68: =AE68/$AE$71 -> 0.44736842 | AD68: Q3 | AE68: =SUMIF($AE$34:$AE$39,$AD68,$AD$34:$AD$39) -> 1785 | AF68: Q3 | AG68: =SUMIF($AE$40:$AE$59,$AF68,$AD$40:$AD$59) -> 1239 | AH68: =AG68/$AG$71 -> 0.049455155
G69: Q2 | H69: C1 | I69: =SUMIF($D$34:$D$59,H69,$AD$34:$AD$59)/SUM($AD$34:$AD$59) -> 0.13015184 | J69: Q2 | X69: =AG61 -> 5431917.3 | Y69: =X69 -> 5431917.3 | AC69: =AE69/$AE$71 -> 0 | AD69: Q4 | AE69: =SUMIF($AE$34:$AE$39,$AD69,$AD$34:$AD$39) -> 0 | AF69: Q4 | AG69: =SUMIF($AE$40:$AE$59,$AF69,$AD$40:$AD$59) -> 462 | AH69: =AG69/$AG$71 -> 0.018440905
G70: Q2 | H70: B2 | I70: =SUMIF($D$34:$D$59,H70,$AD$34:$AD$59)/SUM($AD$34:$AD$59) -> 0.17570499 | J70: Q2 | Y70: =1-Y69/Y68 -> 0.63921649 | AC70: =AE70/$AE$71 -> 0.23157895 | AD70: Q5 | AE70: =SUMIF($AE$34:$AE$39,$AD70,$AD$34:$AD$39) -> 924 | AF70: Q5 | AG70: =SUMIF($AE$40:$AE$59,$AF70,$AD$40:$AD$59) -> 462 | AH70: =AG70/$AG$71 -> 0.018440905
G71: Q1 | H71: B1 | I71: =SUMIF($D$34:$D$59,H71,$AD$34:$AD$59)/SUM($AD$34:$AD$59) -> 0.29934924 | J71: Q1 | X71: =X69/(1-40%) -> 9053195.5 | AE71: =SUM(AE66:AE70) -> 3990 | AG71: =SUM(AG66:AG70) -> 25053
G72: Q1 | H72: A5 | I72: =SUMIF($D$34:$D$59,H72,$AD$34:$AD$59)/SUM($AD$34:$AD$59) -> 0.22704266 | J72: Q1 | X72: =X71/AD61 -> 288.62681 | AG72: =AE71+AG71 -> 29043 | AH72: =AG72*1.08 -> 31366.44
AE73: =AE71*1.08 -> 4309.2 | AG73: =AG71*1.08 -> 27057.24
H74: On/Off | I74: =SUMIF(E34:E59,E34,AD34:AD59)/AD60 -> 0.1373825 | AE74: =AE73+AG73 -> 31366.44
N75: 74 | AE75: =C61 -> 10872146
N76: =N75*I74 -> 10.166305 | AE76: =AE75/AE74 -> 346.61716
AE77: =AE76/8 -> 43.327145

Sheet Important Links
A1: https://cloud.google.com/bigquery-transfer/docs/data-warehouse-migration-overview | K1: BigQuery Data Transfer Service
A2: https://www.youtube.com/watch?v=lc68XluDeH4 | K2: Special migration agent
A3: https://cloud.google.com/bigquery-transfer/docs/teradata-migration
B4: Foundation | D4: Network
D5: Environment
D6: IAM
D7: Cloud Build Teraform
D8: Souce Repo
D9: Cloud DNS
D10: Partner Interconnect
D11: Cloud Operations Suite
D14: Automated TD2BQ transfer agent
D16: Pelican
A25: DataSet | B25: Schema | C25: `--> Location

Sheet TOC
A1: PPT Response
A2: Slide # | B2: Sub Chapter | C2: Owner | D2: Contributor | E2: Reviewers
A3: 1 | B3: Company stats (I&D & GCP capabilities)
A4: 2 | B4: Understanding your objectives & Value Proposition
A5: 3 | B5: Current V/s Proposed Solution Architecture & merits
A6: 4 | B6: Our Data ,Schema, Code Migration Strategy
A7: 5 | B7: Target System Migration Strategy | C7: CIS | F7: Spot, SAP BO, Tableau, SF,Talend,SAP IBP, Altryx
A8: 6 | B8: Proposed End to End GCP Architecture
A9: 7 | B9: Our high level testing strategy to gain data trust on migration
A10: 8 | B10: Proposed implementation timelines
A11: 9 | B11: Tools & Accelerators to expedite migration process
A12: 10 | B12: Possible risks & mitigation plans
A13: 11 | B13: Pricing & Commercials
A14: 12 | B14: Key Assumptions
A15: 13 | B15: Fit Gap Analysis & Due Diligence Approach
A16: 14 | B16: Case Studies with successful migration done in the past
A17: 15 | B17: Case Studies with successful migration done in the past

Sheet Questions & Clarifications
A1: Sr# | B1: Questions | C1: Clarifications by Bayer
A2: 1 | B2: Can you specify version of Teradata used on premise.?
A3: 2 | B3: How data from Stage to Core & finally to Access layer is being propagated currently .? Are you using Informatica or BTEQ scripts for the same.?
A4: 3 | B4: What is your preferred data repository in GCP i.e. Snowflake, Google Big Query.?
A5: 4 | B5: What existing services are up & running on current GCP platform you may want to leverage in this program.?
A6: 5 | B6: Is it safe to assume 3rd party target system owners i.e. Cast Iron (Sales Force, ADW) will retrofit small changes as needed in their systems post migration.?
A7: 6 | B7: Since Bayer already have subscription for GCP is it safe to assume cost for licensing, hosting and support will be borne by Bayer.?
A8: 7 | B8: Can we know how we need to design waves in the high level project timelines.? Can you provide us with high level inputs to logically group supplied volumetrics in to the waves.?
A9: 8 | B9: Can you able to clarify, what are expected services for retiring Teradata EDW platform from the supplier.?
A10: 9 | B10: What would be the scope of migration for down stream Cast Iron (Salesforce) & ADW migration, do these systems to be migrated on GCP, if so, can you please elaborate detail scope .?
A11: 10 | B11: Scope of Informatica is to limited to orchestrate data load with Tera Data Stored SQLs in BTEQ scripts only.? Or otherwise please specify how Informatica is leveraged currently.?
A12: 11 | B12: Please specify Informatica version used currently.?
A13: 12 | B13: Is it safe to assume all existing ETL interfaces & reports should be re-used with minimal retrofication for this program with repointing to the GCP environment as is.?
... A18: 17 | B18: Can you able to specify how many tables/entities are available in access layer.?
